{"\ue8da": "\u7b49", "\ue251": "\u9762", "\ue808": "\u6587", "\uea28": "\u6240", "\ue8a5": "\u88ab", "\ue38f": "\u548c", "\uea45": "\u9053", "\ue148": "\u679c", "\ue3d5": "\u524d", "\ue6c1": "\u751f", "\ueff3": "\u540e", "\ue05b": "\u6210", "\uec3a": "\u65f6", "\uee3e": "\u6253", "\ue8f1": "\u53f2", "\uebc6": "\u4f1a", "\ue077": "\u4eec", "\ue214": "\u5148", "\ue81c": "\u5bf9", "\ue8ec": "\u4ece", "\uec5f": "\u5730", "\ue9ec": "\u6b64", "\ue1c3": "\u5f53", "\ue67b": "\u6b63", "\uecf5": "\u5316", "\ue21d": "\u6765", "\ueb86": "\u5927", "\ue51f": "\u4f5c", "\uec05": "\u4ec0", "\uefe0": "\u91cd", "\ue07a": "\u5f00", "\ue045": "\u5199", "\ue676": "\u5c11", "\ue69f": "\u5206", "\uef6d": "\u7740", "\ueb84": "\u5916", "\ue507": "\u4e2a", "\uefb4": "\u542c", "\uece4": "\u5f97", "\ue1e2": "\u4e4b", "\ue7eb": "\u513f", "\ueb82": "\u6700", "\uefcb": "\u540c", "\ue96f": "\u4e0e", "\ue67a": "\u81ea", "\ued13": "\u6709", "\uea75": "\u5173", "\uea73": "\u5230", "\ue189": "\u7ecf", "\ue79f": "\u7b2c", "\uec3f": "\u5e76", "\ue21f": "\u884c", "\ued43": "\u5df2", "\ue519": "\u91cc", "\ue0b7": "\u80fd", "\uec54": "\u4e16", "\ue5c0": "\u5176", "\ued4d": "\u95e8", "\ue799": "\u767d", "\uee25": "\u4e3b", "\ue911": "\u4e48", "\ue878": "\u8fd8", "\ue812": "\u897f", "\ue877": "\u89c1", "\ueccf": "\u8d70", "\ue5b5": "\u8981", "\ueaf5": "\u5411", "\ueee8": "\u51fa", "\ue561": "\u8fdb", "\uea54": "\u7684", "\ue6b5": "\u8eab", "\uebf4": "\u65b0", "\uebb0": "\u5973", "\uefb2": "\u4f46", "\ue03d": "\u601d", "\ue391": "\u65b9", "\uefde": "\u5b9a", "\ue631": "\u4ed6", "\uef07": "\u4e5f", "\ueb20": "\u6c14", "\ue051": "\u611f", "\ue319": "\u8001", "\ue83b": "\u79cd", "\ueac9": "\u56de", "\ue39a": "\u4e8b", "\ue7db": "\u4e66", "\ue9eb": "\u5f88", "\uede6": "\u6027", "\ue286": "\u516c", "\ue658": "\u5c0f", "\ue728": "\u662f", "\ue39d": "\u5929", "\ue9b2": "\u5168", "\uecea": "\u6211", "\uebd5": "\u5fc3", "\ued10": "\u770b", "\ue114": "\u4e8e", "\ued4e": "\u5728", "\ue6bf": "\u624b", "\uea01": "\u70b9", "\ue341": "\u53c8", "\ue3e5": "\u660e", "\ue0bf": "\u5b9e", "\uecb1": "\u66f4", "\ue16d": "\u597d", "\uec75": "\u7528", "\ue63a": "\u58f0", "\uea52": "\u7406", "\ue156": "\u76f8", "\ue33e": "\u4f60", "\ueab8": "\u5b66", "\ueb05": "\u957f", "\ue1ad": "\u95f4", "\ueb43": "\u522b", "\ue1ba": "\u8d77", "\ued6c": "\u60c5", "\uecfa": "\u90fd", "\ue268": "\u73b0", "\ue6bc": "\u7ed9", "\uef7e": "\u7b11", "\uedf8": "\u90a3", "\uee6f": "\u4eba", "\uee80": "\u592a", "\ue692": "\u8bba", "\uefe2": "\u4ee5", "\ue259": "\u4e9b", "\ue1de": "\u5b50", "\ue435": "\u56e0", "\ued05": "\u4e3a", "\uecdd": "\u6559", "\ue2ab": "\u591a", "\uef3d": "\u4e0d", "\ue3a2": "\u4e8c", "\ue620": "\u90e8", "\ue82e": "\u5979", "\ueffa": "\u8bdd", "\ue7b7": "\u4e00", "\ue205": "\u5934", "\ue0ac": "\u7531", "\ue40b": "\u5bb6", "\ue1c2": "\u529b", "\uedd2": "\u53ea", "\ueda8": "\u6cd5", "\ue1b6": "\u795e", "\uee26": "\u5341", "\ue07e": "\u5982", "\ue138": "\u4e0a", "\ue64c": "\u56db", "\ue45c": "\u628a", "\ue665": "\u672c", "\ue729": "\u53e3", "\ue786": "\u65e0", "\ue7bd": "\u540d", "\ued54": "\u5df1", "\uedd8": "\u53ef", "\uefb3": "\u51e0", "\ue45b": "\u77e5", "\ue78f": "\u53bb", "\ue500": "\u4f7f", "\ue00d": "\u4e49", "\ued4b": "\u4e0b", "\ue001": "\u4e2d", "\ue14c": "\u7279", "\ued3d": "\u518d", "\ue604": "\u8fd9", "\ue50b": "\u8005", "\ue9bc": "\u4e86", "\uef31": "\u5b83", "\ue805": "\u4fbf", "\uebd1": "\u7269", "\ued74": "\u4f55", "\ue109": "\u793e", "\ueea4": "\u5c06", "\ueb67": "\u8fc7", "\ue1b5": "\u7136", "\ue43e": "\u5c31", "\ue5a1": "\u4e09", "\ued45": "\u5e74", "\ue013": "\u6b7b", "\ue43c": "\u800c", "\ue560": "\u9ad8", "\ue92b": "\u5374", "\ue33b": "\u4ee3", "\ue208": "\u4f53", "\uec26": "\u610f", "\ue894": "\u95ee", "\ue6d2": "\u8bf4", "\ue372": "\u771f", "\ue8bd": "\u624d", "\ueaa4": "\u6837", "\ue8d8": "\u773c", "\ue327": "\u60f3", "\uecc4": "\u6c11", "\ue29e": "\u4e24", "\ue646": "\u6ca1", "\ue889": "\u52a8", "\uede5": "\u7f8e", "\ue563": "\u56fd", "\ue9e0": "\u53d1", "\uecb6": "\u65e5"}