{"\ue62f": "\u6837", "\ue3f6": "\u53f2", "\uec87": "\u65e5", "\ue05b": "\u5728", "\ue4d0": "\u771f", "\uead2": "\u5929", "\ue346": "\u5b9e", "\uec6a": "\u5b83", "\uef29": "\u4e66", "\uec55": "\u679c", "\ue15c": "\u591a", "\ueebc": "\u8bf4", "\ued46": "\u91cc", "\ue94f": "\u5b50", "\ueaac": "\u6c14", "\ue426": "\u53bb", "\uec9b": "\u5230", "\ue4d6": "\u767d", "\uee97": "\u795e", "\uea05": "\u8eab", "\uebcf": "\u6b64", "\uee50": "\u5f00", "\uefd9": "\u5c31", "\uee58": "\u89c1", "\ue2a6": "\u529b", "\ue763": "\u4eec", "\ue171": "\u601d", "\uea7e": "\u8bba", "\ue9b0": "\u4fbf", "\ue971": "\u8d77", "\ue1e1": "\u65b9", "\ue48e": "\u8fd8", "\uec9c": "\u7269", "\ue65e": "\u5c0f", "\ue7fd": "\u513f", "\ue8a2": "\u5927", "\ue6dd": "\u4e48", "\uec08": "\u4ee5", "\ue026": "\u4e3b", "\ue902": "\u80fd", "\ue6a1": "\u897f", "\ue7cc": "\u4e2d", "\ue9f8": "\u6027", "\uef99": "\u518d", "\uedf3": "\u91cd", "\uea62": "\u6ca1", "\uebc2": "\u8fdb", "\ue685": "\u4e0e", "\ue24d": "\u95e8", "\uea24": "\u6709", "\ue161": "\u5b9a", "\ue9a2": "\u8bdd", "\ue56e": "\u660e", "\uefc3": "\u4ec0", "\ue12b": "\u7136", "\ue9bf": "\u624b", "\ueeda": "\u95ee", "\ue319": "\u540d", "\ueebd": "\u5934", "\uee65": "\u73b0", "\ue481": "\u5341", "\ue8bb": "\u8001", "\ue213": "\u6b7b", "\ue608": "\u4e86", "\uea22": "\u4f60", "\ue136": "\u56fd", "\uec7c": "\u5b66", "\uea51": "\u957f", "\ue609": "\u4e16", "\uea77": "\u6587", "\ueb13": "\u4e09", "\ue1a7": "\u4e00", "\uea09": "\u5206", "\ue961": "\u8d70", "\ued99": "\u5973", "\uecaf": "\u4e9b", "\ue55a": "\u5411", "\uecdf": "\u540c", "\ue23c": "\u8fd9", "\ue7e4": "\u4e2a", "\ue7ed": "\u60f3", "\ue7aa": "\u751f", "\ue236": "\u8005", "\ue80b": "\u56e0", "\ue7c8": "\u5f97", "\ue7f9": "\u4f53", "\ue9e2": "\u53ea", "\ue2de": "\u53c8", "\uefe8": "\u66f4", "\uefef": "\u611f", "\uebd0": "\u592a", "\ueda7": "\u4ed6", "\uec0b": "\u6253", "\ue8b3": "\u90fd", "\ue50e": "\u662f", "\ue333": "\u51fa", "\uef9f": "\u9762", "\uec4f": "\u542c", "\uedc1": "\u4e3a", "\uef2e": "\u672c", "\ue3ae": "\u624d", "\ue689": "\u4eba", "\ued34": "\u6700", "\ue2b4": "\u4f55", "\ueb5f": "\u90a3", "\ue493": "\u597d", "\uec16": "\u770b", "\ue0e5": "\u800c", "\ue75f": "\u5e76", "\ue91d": "\u7531", "\uea54": "\u4e8e", "\ued6a": "\u610f", "\ue375": "\u4f46", "\ue3be": "\u81ea", "\ueb38": "\u5f88", "\ue4c7": "\u5374", "\ue6ce": "\u6b63", "\ue6ac": "\u4e0d", "\ue99b": "\u53e3", "\uea33": "\u4ee3", "\ue30b": "\u58f0", "\ue184": "\u5e74", "\uee98": "\u5c11", "\ue4e6": "\u4e0a", "\ue344": "\u4e24", "\uee60": "\u7b49", "\uef49": "\u522b", "\uee06": "\u5316", "\ue829": "\u6240", "\ue0b9": "\u5979", "\ued31": "\u6765", "\ue077": "\u4e49", "\ue452": "\u7ecf", "\ue9c0": "\u7279", "\ue787": "\u4e8c", "\ue513": "\u524d", "\ue886": "\u516c", "\uefb6": "\u4e0b", "\uedc7": "\u5bb6", "\ue10b": "\u7b11", "\ue9a1": "\u7740", "\ue687": "\u4e5f", "\uecf2": "\u7ed9", "\ue4e3": "\u4ece", "\ue6e7": "\u5f53", "\ue815": "\u9053", "\ued82": "\u4e4b", "\uefed": "\u884c", "\ue0f8": "\u5199", "\ue5d7": "\u65b0", "\ueb76": "\u5173", "\ue722": "\u56db", "\ue2e3": "\u7528", "\uee90": "\u5bf9", "\uef46": "\u5168", "\ue5db": "\u60c5", "\uecd0": "\u5df1", "\uedb0": "\u8fc7", "\ue3a9": "\u5fc3", "\uedaf": "\u51e0", "\ue1c2": "\u6559", "\ue2ab": "\u540e", "\ue8d4": "\u6211", "\ue26d": "\u7684", "\ue6bb": "\u4e8b", "\ue7fc": "\u53ef", "\ueea1": "\u76f8", "\ue469": "\u53d1", "\ue794": "\u95f4", "\ue7a4": "\u7f8e", "\ue5ae": "\u5176", "\ue2c8": "\u4f7f", "\ued0e": "\u90e8", "\ue103": "\u6cd5", "\ue5d2": "\u793e", "\ue181": "\u773c", "\ue231": "\u5730", "\ue6e2": "\u5df2", "\ue1a5": "\u79cd", "\ue374": "\u65e0", "\ue803": "\u7b2c", "\ue852": "\u548c", "\ue32a": "\u5916", "\uebbf": "\u628a", "\ue629": "\u6210", "\uef0e": "\u7406", "\ue556": "\u52a8", "\ue98b": "\u70b9", "\ue7f7": "\u8981", "\ue72f": "\u77e5", "\ue9e3": "\u5982", "\uec86": "\u6c11", "\ue5ba": "\u88ab", "\uea9f": "\u4f1a", "\uea38": "\u65f6", "\ue72a": "\u5148", "\ue88e": "\u4f5c", "\uebf6": "\u5c06", "\uef74": "\u56de", "\uea48": "\u9ad8"}