{"\ueb78": "\u8bba", "\uef2f": "\u5916", "\ue4fb": "\u7740", "\uebd9": "\u5173", "\ue3cf": "\u76f8", "\uefd2": "\u4eba", "\uef8c": "\u4fbf", "\ue797": "\u7ecf", "\ue77f": "\u5973", "\ued73": "\u58f0", "\ue880": "\u81ea", "\ueee0": "\u5730", "\ue223": "\u6c14", "\ueba1": "\u5c31", "\ue5ea": "\u8d70", "\uefcc": "\u529b", "\ueb3f": "\u65b9", "\uec17": "\u73b0", "\ue981": "\u8bf4", "\ue6c1": "\u6210", "\ue92b": "\u8fc7", "\ueb5d": "\u611f", "\uee64": "\u522b", "\uea3c": "\u7531", "\ue6f4": "\u4e0d", "\ue23b": "\u53bb", "\uebcf": "\u7f8e", "\ue0c5": "\u624b", "\uec1a": "\u5374", "\ue710": "\u542c", "\uec77": "\u548c", "\ue6a9": "\u95e8", "\ue71c": "\u5929", "\ue25d": "\u513f", "\uea9a": "\u6027", "\ue4e0": "\u8005", "\ue4ee": "\u56fd", "\ue946": "\u6709", "\ued92": "\u7b2c", "\ue60f": "\u4f7f", "\ue499": "\u6ca1", "\ue4b5": "\u53ea", "\uec07": "\u751f", "\uef6a": "\u4e8b", "\ue4f8": "\u5979", "\ue4f1": "\u8bdd", "\ue2fc": "\u5168", "\uea62": "\u66f4", "\ueb84": "\u5e76", "\uec6e": "\u770b", "\ue68c": "\u80fd", "\ue129": "\u51fa", "\ue790": "\u6559", "\ue24a": "\u6253", "\ue295": "\u4ee3", "\ue1d6": "\u4e86", "\ued11": "\u624d", "\ue959": "\u4e09", "\uec06": "\u6c11", "\ueffc": "\u5b66", "\ue5f2": "\u5f97", "\ue13f": "\u4e16", "\uebb2": "\u89c1", "\ue40f": "\u4ed6", "\ueb03": "\u5f00", "\ue936": "\u90fd", "\ue3ab": "\u6b64", "\uee2c": "\u4e9b", "\ue052": "\u884c", "\ue877": "\u524d", "\uea22": "\u4e2a", "\ueeb7": "\u5b50", "\ueef0": "\u70b9", "\ue308": "\u77e5", "\ue1fd": "\u5c06", "\ue433": "\u897f", "\uee68": "\u9762", "\uebb3": "\u91cc", "\uef28": "\u5df1", "\ueef8": "\u672c", "\ue9a6": "\u7528", "\ue194": "\u795e", "\uea6d": "\u5176", "\ue7c8": "\u4ec0", "\uea75": "\u516c", "\ue70b": "\u662f", "\uebd0": "\u5934", "\ue543": "\u7b11", "\ue824": "\u53d1", "\ueb90": "\u4f60", "\uedf2": "\u6211", "\ue290": "\u773c", "\ue56d": "\u53c8", "\ueaae": "\u8eab", "\ue9ad": "\u591a", "\ue160": "\u5c11", "\uec89": "\u679c", "\ue50d": "\u5148", "\uee1c": "\u4f1a", "\ueaa0": "\u592a", "\uea1c": "\u7ed9", "\ue8ca": "\u5fc3", "\ue8e1": "\u5df2", "\ue116": "\u5f88", "\ue8b2": "\u4f55", "\uebfd": "\u53e3", "\uef36": "\u65b0", "\uefa8": "\u9053", "\ue352": "\u4f46", "\ue2d1": "\u6cd5", "\ue399": "\u56e0", "\ue33b": "\u957f", "\uecda": "\u793e", "\ue11e": "\u4ece", "\ue066": "\u5b83", "\ue59b": "\u90e8", "\ued1e": "\u518d", "\ue189": "\u88ab", "\ue184": "\u628a", "\ueb9a": "\u8fd9", "\ue534": "\u65f6", "\ue7be": "\u7406", "\ue0d1": "\u597d", "\uebfa": "\u610f", "\ue197": "\u4e2d", "\ue859": "\u540d", "\ue1f6": "\u7269", "\ue390": "\u540e", "\uef75": "\u540c", "\ue964": "\u90a3", "\ueaa9": "\u5316", "\ueb60": "\u767d", "\ueaa4": "\u8981", "\ue078": "\u5199", "\ue56c": "\u4e3a", "\ue834": "\u5230", "\ue8c3": "\u6587", "\ueb8c": "\u660e", "\uefa1": "\u6700", "\uecc0": "\u91cd", "\ue4da": "\u601d", "\uefb8": "\u7136", "\ue676": "\u4e5f", "\ue62a": "\u8fd8", "\ue266": "\u5b9e", "\ueb42": "\u5411", "\ue0a9": "\u4e48", "\ue2fd": "\u4e0e", "\ue944": "\u4e0b", "\ue4cf": "\u56de", "\uebaa": "\u51e0", "\ue723": "\u6b7b", "\uef3b": "\u4e8c", "\uef0c": "\u5f53", "\ue657": "\u771f", "\ued4b": "\u60c5", "\uee9a": "\u60f3", "\ue2c4": "\u53f2", "\ue392": "\u8fdb", "\ue350": "\u7279", "\ued39": "\u9ad8", "\ue3b9": "\u5c0f", "\ueed3": "\u4e00", "\ue5cd": "\u5bb6", "\ue040": "\u8d77", "\ue6cc": "\u5728", "\uefa0": "\u53ef", "\ue181": "\u5b9a", "\ue3cc": "\u65e0", "\ue079": "\u7684", "\ue6c7": "\u4eec", "\uea76": "\u5927", "\ue26b": "\u5982", "\uedcc": "\u6b63", "\ue893": "\u800c", "\ue358": "\u65e5", "\uee17": "\u4e8e", "\ue2df": "\u5e74", "\ue2a7": "\u52a8", "\ue336": "\u4e24", "\ue186": "\u4e4b", "\ueb71": "\u6240", "\ue13c": "\u4f53", "\ue270": "\u7b49", "\ueeb4": "\u95f4", "\ue510": "\u95ee", "\uef4e": "\u56db", "\ue7d0": "\u5206", "\ue61c": "\u8001", "\ue611": "\u4ee5", "\uef57": "\u4e49", "\uefe3": "\u5bf9", "\ue265": "\u5341", "\ue550": "\u4e0a", "\ue478": "\u6765", "\ue9c1": "\u6837", "\ue99f": "\u4f5c", "\ue4dd": "\u79cd", "\ue3c7": "\u4e66", "\ue899": "\u4e3b"}