{"\ue37f": "\u624d", "\ue84b": "\u542c", "\uecc6": "\u7528", "\uef14": "\u56de", "\ue409": "\u6b63", "\ue1eb": "\u7ecf", "\ue93f": "\u4e66", "\ue6d1": "\u5b66", "\ued3b": "\u4ed6", "\ue0ab": "\u767d", "\ue3aa": "\u5c11", "\ue694": "\u4ec0", "\ue9ad": "\u518d", "\uea7b": "\u88ab", "\ue8a1": "\u95e8", "\ueeb6": "\u8981", "\ue683": "\u522b", "\ueb7b": "\u611f", "\ue1dd": "\u770b", "\ue738": "\u5730", "\ue8ec": "\u5f97", "\ue19b": "\u672c", "\ue1f3": "\u4e8c", "\uee81": "\u91cc", "\uec02": "\u65b0", "\uea24": "\u4e3a", "\ue05e": "\u4f5c", "\ue996": "\u90a3", "\ue3fb": "\u4e0a", "\ue782": "\u5934", "\uebbd": "\u6c14", "\uecb6": "\u6837", "\ue022": "\u53f2", "\ue2b7": "\u524d", "\uec12": "\u65f6", "\uec37": "\u8001", "\ue36e": "\u4ee5", "\ue95f": "\u58f0", "\ue0b8": "\u5148", "\ue237": "\u76f8", "\ue7a1": "\u6587", "\ueb12": "\u7b49", "\uecf5": "\u4eec", "\uee60": "\u6cd5", "\ue994": "\u5f00", "\uee82": "\u5316", "\uecb1": "\u4f1a", "\ued08": "\u529b", "\ueca6": "\u771f", "\ue3ab": "\u5fc3", "\ue2c8": "\u8005", "\uef0e": "\u6559", "\ue0aa": "\u8fc7", "\ue198": "\u77e5", "\ue3f8": "\u662f", "\ue539": "\u8d77", "\ue93b": "\u624b", "\ue295": "\u5bb6", "\ueb13": "\u6765", "\ue1da": "\u89c1", "\ue81a": "\u4e8b", "\ue37b": "\u4eba", "\ue3f0": "\u4e2d", "\ue4b8": "\u6b7b", "\ueade": "\u7f8e", "\ue094": "\u4e48", "\ue5d4": "\u5b9e", "\uef21": "\u56db", "\ue99d": "\u795e", "\uee84": "\u8eab", "\ue39a": "\u5199", "\ue20a": "\u4e4b", "\ue6e1": "\u5bf9", "\ue597": "\u6b64", "\ue1ad": "\u53d1", "\ue453": "\u8bdd", "\ue5e9": "\u4f53", "\ue63a": "\u5e76", "\ue614": "\u7b11", "\ue009": "\u591a", "\ue3b0": "\u7b2c", "\ue690": "\u5c0f", "\ue7d0": "\u800c", "\ue106": "\u60c5", "\uea35": "\u70b9", "\ue98e": "\u7136", "\ue71e": "\u9762", "\uef0b": "\u80fd", "\ue686": "\u7269", "\ue313": "\u773c", "\ue4a3": "\u4f7f", "\uea88": "\u7406", "\ue268": "\u5979", "\ue523": "\u5c31", "\uea3f": "\u4ee3", "\ue922": "\u53e3", "\uec95": "\u5728", "\uecfb": "\u5168", "\ued29": "\u516c", "\ue545": "\u53ef", "\uebc8": "\u7279", "\ue35c": "\u5b83", "\ue96b": "\u610f", "\uef90": "\u897f", "\ue8fe": "\u5f88", "\ue819": "\u6253", "\ue74b": "\u5176", "\ue53a": "\u4e24", "\ue104": "\u6211", "\ueace": "\u90fd", "\ue642": "\u513f", "\ue602": "\u6240", "\ue51d": "\u60f3", "\uecac": "\u8fd9", "\ueafa": "\u4e16", "\ue85d": "\u5173", "\ue754": "\u884c", "\ue9e7": "\u5411", "\ue70d": "\u5374", "\ue856": "\u601d", "\ue468": "\u4f55", "\ue8e7": "\u6027", "\ue6eb": "\u4fbf", "\ue2fa": "\u7ed9", "\ue812": "\u4ece", "\ue316": "\u5c06", "\ue278": "\u4e0e", "\uee34": "\u5982", "\ue6f9": "\u4e5f", "\uec94": "\u6210", "\ue74c": "\u679c", "\uebe5": "\u8bba", "\ue758": "\u65e0", "\ue75a": "\u592a", "\uea62": "\u6c11", "\ueeb3": "\u5916", "\ue4c3": "\u4e0b", "\ue80c": "\u7531", "\ue1ce": "\u4e86", "\uec6b": "\u4f46", "\ue2bf": "\u4e9b", "\ueda8": "\u73b0", "\ue274": "\u90e8", "\ue074": "\u5f53", "\ue39f": "\u5927", "\ued59": "\u4e8e", "\ue3c0": "\u5e74", "\ue69d": "\u56e0", "\ued28": "\u540d", "\uedcb": "\u51fa", "\ue31c": "\u5b50", "\ue408": "\u5206", "\ue53e": "\u65b9", "\ueca0": "\u540e", "\ue6af": "\u751f", "\ue5fe": "\u53c8", "\ue90d": "\u6700", "\uee3f": "\u4e09", "\uecd7": "\u597d", "\ue70c": "\u5df2", "\uefdf": "\u95f4", "\ue1f4": "\u56fd", "\uefd0": "\u793e", "\ue15c": "\u4e0d", "\ue2c7": "\u53bb", "\ue2da": "\u4e49", "\uee4f": "\u660e", "\ue43e": "\u7740", "\ue0d0": "\u9053", "\ue542": "\u5b9a", "\ueaa8": "\u52a8", "\ued22": "\u4e2a", "\uee62": "\u8fdb", "\ue9cc": "\u95ee", "\ue0df": "\u4e3b", "\ue711": "\u9ad8", "\ue3c2": "\u65e5", "\ue5d9": "\u53ea", "\ueb42": "\u51e0", "\ue96e": "\u957f", "\ued9f": "\u4f60", "\ue87a": "\u6709", "\ued54": "\u79cd", "\uec2b": "\u540c", "\ue1bf": "\u5973", "\ue7a2": "\u8fd8", "\ueb49": "\u81ea", "\ued20": "\u628a", "\uee98": "\u6ca1", "\uebb1": "\u5230", "\ued13": "\u7684", "\uef6f": "\u66f4", "\ue744": "\u91cd", "\ue3e4": "\u4e00", "\ue0bb": "\u8bf4", "\ue03e": "\u5929", "\uee2e": "\u8d70", "\uecc1": "\u5df1", "\ue5f8": "\u548c", "\ue611": "\u5341"}