{"\ue978": "\u4e9b", "\uee4c": "\u672c", "\ue660": "\u4e49", "\ue366": "\u52a8", "\uea3e": "\u4f55", "\uedc6": "\u662f", "\uee33": "\u56db", "\uee24": "\u56fd", "\uecda": "\u5199", "\ue0d0": "\u53c8", "\ue936": "\u4e5f", "\ue623": "\u4f7f", "\ue856": "\u53bb", "\ue64f": "\u5b9e", "\uefc9": "\u4f1a", "\ue49f": "\u5148", "\ue483": "\u7ecf", "\uec64": "\u95e8", "\uec31": "\u4e0b", "\uec39": "\u4ece", "\ue768": "\u91cc", "\ue13b": "\u60f3", "\ue0e5": "\u4e2a", "\ue3ab": "\u8981", "\ue580": "\u524d", "\ue2e1": "\u65e0", "\uee09": "\u540e", "\ue2ca": "\u4e8e", "\uefc1": "\u8bdd", "\ue422": "\u53ef", "\ue5e4": "\u5c31", "\ueade": "\u516c", "\ue15d": "\u5979", "\ue3c1": "\u4e66", "\ueb2b": "\u90e8", "\ueabc": "\u60c5", "\ue656": "\u529b", "\ueaab": "\u5230", "\ueff0": "\u4e0a", "\ueba6": "\u7406", "\ue9a1": "\u8fd9", "\uedb6": "\u8d70", "\ue334": "\u4f53", "\ue1cf": "\u4e48", "\ue727": "\u65b9", "\ue295": "\u518d", "\ueb87": "\u767d", "\uec7a": "\u4e0e", "\ue816": "\u5982", "\ue432": "\u795e", "\ue9c9": "\u4e0d", "\ue3b3": "\u5374", "\ue208": "\u53ea", "\ue4cc": "\u9053", "\ue0ac": "\u6210", "\ue1df": "\u80fd", "\ue0e2": "\u542c", "\ue01f": "\u5f53", "\ue7cf": "\u5c06", "\ueb81": "\u79cd", "\ue094": "\u4ec0", "\ueb1d": "\u6cd5", "\ueb48": "\u9ad8", "\ue95d": "\u8fdb", "\ueb14": "\u66f4", "\ue786": "\u5934", "\ueb65": "\u7528", "\ue3e7": "\u5df1", "\ue9ce": "\u4e86", "\ue439": "\u6b64", "\uec0f": "\u7531", "\uee58": "\u592a", "\ue434": "\u91cd", "\ue03b": "\u6709", "\ue835": "\u4e4b", "\ueef5": "\u5929", "\ue1d7": "\u5bf9", "\uea9b": "\u95ee", "\ue283": "\u5b50", "\ued3d": "\u4f46", "\uef68": "\u5927", "\uea41": "\u5176", "\uec3f": "\u5e74", "\ue49c": "\u4f5c", "\ue826": "\u65e5", "\ue0b4": "\u6027", "\ueff1": "\u897f", "\ueaf1": "\u5e76", "\ue9af": "\u793e", "\ue3a0": "\u6b63", "\uea71": "\u601d", "\ueb7e": "\u5316", "\uedf8": "\u70b9", "\uecf5": "\u5168", "\ue327": "\u4ed6", "\ue680": "\u6837", "\ue84a": "\u7f8e", "\uec6c": "\u53d1", "\uebbd": "\u540d", "\ue52f": "\u51fa", "\ue918": "\u597d", "\ueed7": "\u88ab", "\ue593": "\u7684", "\ued70": "\u53e3", "\ue06b": "\u660e", "\ue1c4": "\u53f2", "\ue5c9": "\u770b", "\uec07": "\u8fc7", "\ue77b": "\u4eba", "\ue62e": "\u5f88", "\uecf7": "\u4ee3", "\uede0": "\u6c14", "\ue4ce": "\u6ca1", "\uee7c": "\u5df2", "\ue1c1": "\u8fd8", "\ue742": "\u5c0f", "\uefa5": "\u5b83", "\ue5ff": "\u4e8b", "\uefd1": "\u4ee5", "\uec1a": "\u58f0", "\ue6ba": "\u611f", "\ue0f7": "\u610f", "\uef67": "\u73b0", "\ue58a": "\u7279", "\ue9de": "\u8d77", "\ue6a8": "\u4e2d", "\ue055": "\u5fc3", "\ue6a6": "\u95f4", "\ue989": "\u7b49", "\ue9e9": "\u7ed9", "\uef93": "\u5bb6", "\ue27b": "\u4e3b", "\uec37": "\u6700", "\ue2ec": "\u6253", "\uea7d": "\u679c", "\ue99b": "\u6b7b", "\ue8d5": "\u7740", "\ued80": "\u6559", "\ue412": "\u8001", "\uea0c": "\u5341", "\ue1f8": "\u4e8c", "\ueb34": "\u6587", "\uebd6": "\u8eab", "\ue35f": "\u540c", "\uecfd": "\u5206", "\ueffc": "\u5f97", "\ue723": "\u628a", "\ue292": "\u5173", "\ue6e4": "\u4eec", "\uef7d": "\u5411", "\uebb8": "\u8005", "\uebfa": "\u7b11", "\uefbe": "\u4e3a", "\uee18": "\u56de", "\ue999": "\u5730", "\uedfc": "\u81ea", "\ued99": "\u624b", "\ue9a3": "\u4e24", "\ue8e6": "\u6240", "\ue584": "\u7b2c", "\ue5e5": "\u5c11", "\uefc8": "\u773c", "\ueb71": "\u56e0", "\ue80d": "\u4e00", "\ued59": "\u957f", "\ue431": "\u5b66", "\ue10d": "\u90fd", "\ue23b": "\u7136", "\ue08c": "\u751f", "\ue634": "\u5973", "\ue5ae": "\u4e16", "\ueadb": "\u4fbf", "\ueb9d": "\u8bf4", "\ue2dc": "\u77e5", "\uea1c": "\u6765", "\uea19": "\u624d", "\ue73b": "\u7269", "\ue555": "\u76f8", "\ueac4": "\u6c11", "\uee7b": "\u65f6", "\ue67c": "\u591a", "\ue661": "\u9762", "\ue37e": "\u5f00", "\ueba8": "\u522b", "\ue9a7": "\u5728", "\uefad": "\u65b0", "\uee8e": "\u6211", "\ue7ef": "\u800c", "\uedae": "\u4f60", "\uedb5": "\u884c", "\uefd6": "\u51e0", "\ue151": "\u4e09", "\ue8b9": "\u513f", "\ue5ba": "\u5b9a", "\uef41": "\u90a3", "\ue433": "\u89c1", "\ued81": "\u548c", "\uefb4": "\u8bba", "\ueaec": "\u771f", "\ue315": "\u5916"}