[{"\uefed": "\u795e", "\ue986": "\u518d", "\ue881": "\u4e8b", "\ue7f2": "\u53bb", "\uef0b": "\u601d", "\ued02": "\u4ee3", "\ue680": "\u5173", "\uec21": "\u5c11", "\uea8b": "\u5168", "\ue9b1": "\u7279", "\ue9a0": "\u9762", "\ue9e9": "\u6210", "\ue45c": "\u4e3b", "\uee78": "\u90e8", "\ue926": "\u7136", "\ue9c1": "\u52a8", "\ue544": "\u524d", "\uec9d": "\u8d77", "\ue61b": "\u7406", "\ue316": "\u8fd8", "\ue696": "\u95ee", "\ue520": "\u548c", "\ued3c": "\u660e", "\ue2e0": "\u4e5f", "\ue32f": "\u770b", "\ue7e8": "\u767d", "\ue9d9": "\u6709", "\uec9b": "\u5b9a", "\ue917": "\u53ea", "\uef9d": "\u516c", "\ued4a": "\u51e0", "\ue044": "\u4e16", "\ued20": "\u5979", "\uea8f": "\u7f8e", "\uebbd": "\u5982", "\ueda7": "\u56fd", "\ue69c": "\u611f", "\ue963": "\u77e5", "\ue303": "\u60f3", "\ue74c": "\u771f", "\uefd2": "\u8bdd", "\ue870": "\u4e48", "\ue395": "\u7528", "\ue434": "\u51fa", "\uec1e": "\u65e0", "\ue1db": "\u6b63", "\ue4e1": "\u53e3", "\ue882": "\u5df1", "\ue22d": "\u624b", "\uec08": "\u4e09", "\uec87": "\u5b50", "\ueb20": "\u540e", "\ued97": "\u5fc3", "\ue386": "\u540c", "\ue2ea": "\u5934", "\ueef4": "\u4ee5", "\ue62c": "\u8fd9", "\uec25": "\u5bf9", "\ue7c0": "\u4ece", "\ue572": "\u5b83", "\ue910": "\u95f4", "\ue568": "\u90fd", "\ueaae": "\u8bba", "\uee36": "\u7531", "\ueaea": "\u5df2", "\ue3a2": "\u65f6", "\uef5c": "\u81ea", "\ue1bf": "\u9053", "\ue8af": "\u628a", "\ue0fa": "\u7b49", "\ue80b": "\u5b66", "\ue0ec": "\u4eec", "\ue7e3": "\u5730", "\ued8d": "\u79cd", "\ue2a7": "\u4e0e", "\ue700": "\u5176", "\ue372": "\u6027", "\ued34": "\u5148", "\uec35": "\u5199", "\ue4ca": "\u592a", "\ue35f": "\u6559", "\ue4a1": "\u90a3", "\ue06d": "\u751f", "\uefcb": "\u53d1", "\uea79": "\u542c", "\ue7dd": "\u56de", "\ue808": "\u53c8", "\uef61": "\u6b64", "\ue72a": "\u60c5", "\uee50": "\u80fd", "\ue376": "\u624d", "\ue598": "\u6253", "\ue0dd": "\u8001", "\ue949": "\u662f", "\uecb7": "\u597d", "\ue435": "\u5230", "\ue9dd": "\u8fdb", "\uea7f": "\u672c", "\ue773": "\u7269", "\uebfd": "\u4e9b", "\ueeea": "\u7ed9", "\uea43": "\u5929", "\ue1ec": "\u7b2c", "\uefaf": "\u7740", "\ued0b": "\u88ab", "\ueefe": "\u6cd5", "\ue1b0": "\u5206", "\ue0be": "\u4e66", "\uec51": "\u58f0", "\ued03": "\u56e0", "\ue6db": "\u95e8", "\uefc2": "\u66f4", "\ue0eb": "\u4e0d", "\ue518": "\u5e76", "\ue96b": "\u897f", "\ue1d5": "\u6c14", "\ueee0": "\u679c", "\ue03f": "\u70b9", "\ueca2": "\u4f7f", "\ue40f": "\u5728", "\uefe6": "\u4f46", "\ue928": "\u65b9", "\uecec": "\u4e49", "\ue751": "\u800c", "\ueb74": "\u4e8e", "\uee86": "\u4f60", "\ue49d": "\u4e8c", "\ue49b": "\u9ad8", "\ue5f1": "\u5374", "\ue5e4": "\u5341", "\ue999": "\u540d", "\uebae": "\u4f53", "\ue394": "\u5f00", "\ued1f": "\u6240", "\ue80f": "\u5316", "\ue211": "\u65b0", "\uea59": "\u6211", "\ue790": "\u5973", "\uec5f": "\u73b0", "\uefa7": "\u884c", "\ue390": "\u6c11", "\ue626": "\u5f53", "\ue7eb": "\u53ef", "\uee2c": "\u53f2", "\ueabc": "\u7684", "\ue692": "\u6587", "\ueb17": "\u4e0b", "\uec76": "\u957f", "\ue58c": "\u5f88", "\ue874": "\u76f8", "\ue549": "\u4eba", "\ue8f6": "\u5b9e", "\ue6a9": "\u56db", "\ue221": "\u8bf4", "\ue608": "\u5411", "\ue2aa": "\u5c31", "\uee62": "\u793e", "\ue3cd": "\u610f", "\ue9e1": "\u91cc", "\ue6a3": "\u4f55", "\ue283": "\u4e2d", "\uecee": "\u5c0f", "\ue48c": "\u65e5", "\ue2c8": "\u4e3a", "\ue996": "\u6765", "\uee3e": "\u7ecf", "\ue1ea": "\u5c06", "\ue3e3": "\u529b", "\ued8f": "\u5bb6", "\uec24": "\u513f", "\ued87": "\u8eab", "\ue70e": "\u4e86", "\ue785": "\u7b11", "\ued0a": "\u5927", "\ue8df": "\u773c", "\ueffc": "\u5e74", "\ue5b9": "\u89c1", "\ue448": "\u5916", "\ue2f2": "\u4e0a", "\ue1e4": "\u4fbf", "\ue5b2": "\u522b", "\ue8b7": "\u91cd", "\ue971": "\u591a", "\ue0a1": "\u6700", "\ued08": "\u4f5c", "\ue5ba": "\u6ca1", "\uecc0": "\u8005", "\ue5db": "\u6837", "\ueba8": "\u4ed6", "\ue3d3": "\u4e4b", "\uee98": "\u8981", "\ue943": "\u8fc7", "\ue0a8": "\u4f1a", "\ue7a1": "\u4ec0", "\uefd1": "\u5f97", "\ue52e": "\u8d70", "\ue210": "\u6b7b", "\uee10": "\u4e2a", "\ue02b": "\u4e00", "\ue198": "\u4e24"}, 193.45273178476506]