{"\ue02f": "\u4e00", "\ue6ba": "\u591a", "\ue8b7": "\u4eba", "\ueb44": "\u4f5c", "\ue918": "\u4e0b", "\ue791": "\u60c5", "\ue82b": "\u73b0", "\ue98d": "\u751f", "\ue14d": "\u95e8", "\ue182": "\u4e16", "\ue3da": "\u90a3", "\ue9cc": "\u65f6", "\ue78a": "\u6b7b", "\ueee5": "\u6cd5", "\ueab0": "\u51e0", "\ued46": "\u897f", "\ue92b": "\u5411", "\ue246": "\u5979", "\ue1f2": "\u6027", "\ue2d9": "\u90e8", "\uea3c": "\u513f", "\ue5dd": "\u4e09", "\ue6da": "\u58f0", "\ue489": "\u4f53", "\ue326": "\u5b50", "\ue780": "\u4e0d", "\uea81": "\u597d", "\uee1d": "\u66f4", "\ue1e0": "\u65e5", "\ued15": "\u65b9", "\ueb45": "\u4e8b", "\ue459": "\u4fbf", "\ue015": "\u5934", "\ueb51": "\u518d", "\uecb3": "\u5176", "\ue5df": "\u524d", "\ue592": "\u7406", "\uec08": "\u4e8c", "\ue902": "\u540e", "\ue6d8": "\u5f53", "\uea64": "\u4e0e", "\ue765": "\u660e", "\uec92": "\u8981", "\ue703": "\u56db", "\ueb84": "\u53c8", "\ue314": "\u770b", "\ueffa": "\u52a8", "\ue5b0": "\u7ed9", "\ue1af": "\u53bb", "\uedef": "\u56de", "\ue64a": "\u56e0", "\ue891": "\u5c06", "\ue793": "\u9762", "\ue0ae": "\u624d", "\uec76": "\u8bdd", "\ue9dc": "\u5e76", "\ue8f2": "\u5230", "\uee0a": "\u628a", "\ue00e": "\u5168", "\ue2ee": "\u4e2a", "\uef85": "\u4e4b", "\ue8d9": "\u662f", "\ue0c9": "\u5df1", "\uea83": "\u88ab", "\uec2a": "\u8d70", "\uef90": "\u7279", "\ueec2": "\u5982", "\ue74d": "\u4e3a", "\ueda5": "\u4ece", "\ue08e": "\u601d", "\ueb7d": "\u56fd", "\ue253": "\u4ec0", "\ue35a": "\u5df2", "\ue769": "\u5973", "\ue910": "\u51fa", "\ueb7c": "\u4e0a", "\uea1f": "\u4ee5", "\uea44": "\u5b83", "\ue175": "\u53f2", "\ued88": "\u4e86", "\ued48": "\u548c", "\uecb5": "\u4f46", "\ue333": "\u592a", "\ue538": "\u6700", "\ue016": "\u4e3b", "\ue548": "\u5374", "\ue07d": "\u5c31", "\ue196": "\u5e74", "\ue06b": "\u5b66", "\uebf5": "\u5f97", "\ue05d": "\u6765", "\ue2b4": "\u91cc", "\uedb5": "\u5316", "\ue47e": "\u5b9a", "\ue3cd": "\u773c", "\ue141": "\u6ca1", "\ue41f": "\u80fd", "\ue4b9": "\u611f", "\ue699": "\u5148", "\ueb9c": "\u9053", "\ue4c1": "\u542c", "\uefa7": "\u7269", "\ue668": "\u4f1a", "\ueb1e": "\u79cd", "\ue11e": "\u5bf9", "\ue0f1": "\u7b49", "\ue111": "\u4eec", "\ue6b5": "\u65e0", "\uea63": "\u4ed6", "\uecee": "\u6b63", "\uea1d": "\u60f3", "\ue343": "\u4e9b", "\uee94": "\u8fd9", "\uee92": "\u7740", "\ue8f5": "\u91cd", "\ue88c": "\u89c1", "\ued50": "\u7528", "\ue897": "\u679c", "\ueb4a": "\u53ea", "\ue368": "\u8bf4", "\ue72d": "\u5c11", "\ue70f": "\u6b64", "\uea8e": "\u7136", "\ue197": "\u77e5", "\ue225": "\u53e3", "\ue0b2": "\u76f8", "\uecd9": "\u90fd", "\ue04f": "\u7684", "\ue719": "\u95ee", "\ue162": "\u7f8e", "\ue927": "\u5bb6", "\ueb7b": "\u4e5f", "\ue1f8": "\u522b", "\ue518": "\u6211", "\ue8b9": "\u8fd8", "\ue427": "\u5fc3", "\ue4db": "\u5f88", "\ue634": "\u5199", "\uea4f": "\u5173", "\uea85": "\u95f4", "\ue59d": "\u6837", "\ue408": "\u4e48", "\ueae3": "\u4e8e", "\ue03f": "\u70b9", "\ue9fa": "\u610f", "\ue5fb": "\u4e49", "\ue63e": "\u4f55", "\ue1dc": "\u6c14", "\ue27e": "\u53d1", "\ue89c": "\u540c", "\ued52": "\u5730", "\ue8a0": "\u5b9e", "\ueba5": "\u8001", "\ue2fd": "\u5c0f", "\ue8d4": "\u529b", "\ue42f": "\u65b0", "\uec45": "\u6253", "\ue16d": "\u4ee3", "\uee02": "\u9ad8", "\ue243": "\u624b", "\ueb52": "\u884c", "\uecb2": "\u516c", "\ued47": "\u8eab", "\ue1a6": "\u6c11", "\ue930": "\u540d", "\ueb2b": "\u4e2d", "\ue07f": "\u4e66", "\ue69e": "\u771f", "\ue8f3": "\u53ef", "\ueed3": "\u7ecf", "\ue07a": "\u8fc7", "\ue48a": "\u7b11", "\ue074": "\u4f7f", "\uedc0": "\u957f", "\ue24b": "\u6559", "\ue480": "\u672c", "\ue6a5": "\u8bba", "\uee00": "\u6587", "\ue29f": "\u795e", "\ue0a5": "\u4f60", "\uee4e": "\u8005", "\ue774": "\u793e", "\ue11a": "\u5929", "\ueb6a": "\u767d", "\uecd7": "\u4e24", "\uee9f": "\u8fdb", "\uefe2": "\u81ea", "\ue6cf": "\u5341", "\ue9c3": "\u6240", "\ue691": "\u5206", "\ue84f": "\u800c", "\uebd2": "\u5916", "\ue3ce": "\u5f00", "\ue9b5": "\u5927", "\uead3": "\u6210", "\ue439": "\u5728", "\ue3c6": "\u7b2c", "\ueed1": "\u6709", "\ue76f": "\u8d77", "\ue0bf": "\u7531"}