{"\ue5f7": "\u771f", "\ueb51": "\u95e8", "\ue8de": "\u4e00", "\ue842": "\u8eab", "\ue22c": "\u5c31", "\ue225": "\u5bf9", "\ue40c": "\u518d", "\ue441": "\u53e3", "\uee7e": "\u6559", "\ue9f9": "\u56de", "\ue718": "\u540e", "\ue3a1": "\u91cd", "\uec99": "\u56e0", "\uedf7": "\u8fc7", "\ue924": "\u4eba", "\uee58": "\u5b50", "\ueac7": "\u601d", "\ue2c9": "\u5df2", "\ue9f7": "\u65e5", "\ue26a": "\u5e74", "\ue375": "\u58f0", "\ue3d8": "\u76f8", "\ue2d4": "\u4e86", "\uec19": "\u53ef", "\ue43c": "\u8d70", "\ue2ef": "\u679c", "\uecf4": "\u4e0b", "\uee82": "\u95ee", "\uea66": "\u540d", "\ue3b9": "\u4f7f", "\ue217": "\u542c", "\ued12": "\u8fd9", "\ue6fb": "\u91cc", "\ued1f": "\u7740", "\ued7f": "\u5730", "\ue7ef": "\u8fd8", "\ue5a8": "\u884c", "\ue626": "\u6cd5", "\ue152": "\u624b", "\ue6f5": "\u8005", "\uea04": "\u773c", "\ueaa3": "\u4ee3", "\uebf0": "\u540c", "\ue138": "\u5c06", "\uec3f": "\u5411", "\uec59": "\u9053", "\uec90": "\u6765", "\ue822": "\u5934", "\uefe9": "\u51e0", "\ue06b": "\u7528", "\ue63b": "\u4ece", "\ue3df": "\u6211", "\ue4b0": "\u6700", "\ue652": "\u4f5c", "\ued9c": "\u4eec", "\ue7e6": "\u65e0", "\uea86": "\u9ad8", "\ue494": "\u897f", "\ueb86": "\u5316", "\ue10c": "\u8d77", "\ueaea": "\u5f88", "\uecf8": "\u957f", "\ue94f": "\u662f", "\ue4e8": "\u8981", "\ue734": "\u79cd", "\ue1bc": "\u513f", "\ue99a": "\u4e0d", "\ue546": "\u5929", "\ue63a": "\u628a", "\ue74f": "\u5341", "\ue254": "\u5927", "\ueb73": "\u5168", "\uec26": "\u516c", "\ueff8": "\u51fa", "\ue0f4": "\u8bf4", "\ue86a": "\u5374", "\ue353": "\u8bba", "\uebf2": "\u524d", "\ue46c": "\u5e76", "\ueecc": "\u5f00", "\ue37a": "\u7ed9", "\ue014": "\u5173", "\ue232": "\u4ed6", "\uebe5": "\u65b9", "\ued60": "\u6587", "\ueba4": "\u5df1", "\ue88c": "\u795e", "\ue9e8": "\u522b", "\uea03": "\u4e2a", "\ue020": "\u5728", "\ue8fb": "\u60f3", "\ue901": "\u751f", "\ue463": "\u6b63", "\ue5c9": "\u4e3a", "\ue1e6": "\u89c1", "\ue775": "\u65f6", "\ue316": "\u4e4b", "\ued26": "\u5f53", "\ue956": "\u4ec0", "\ue6d0": "\u4e8e", "\ued16": "\u7b11", "\uebb4": "\u65b0", "\uee5d": "\u5b9e", "\ue161": "\u5fc3", "\ue1cd": "\u5230", "\ue767": "\u591a", "\uec8a": "\u6c14", "\ued08": "\u9762", "\uef32": "\u53d1", "\ue64c": "\u90a3", "\ue85f": "\u5f97", "\ue1c5": "\u4f53", "\ue09a": "\u5b9a", "\ueee7": "\u8fdb", "\ue140": "\u7136", "\ue185": "\u5b66", "\ueb71": "\u52a8", "\ue1bb": "\u624d", "\ueaf8": "\u6253", "\uebed": "\u6b64", "\ue30f": "\u6027", "\ue0fc": "\u5c11", "\ue2cd": "\u90e8", "\ue6d6": "\u7269", "\ue404": "\u73b0", "\ue5ff": "\u4fbf", "\ue47d": "\u77e5", "\ueff6": "\u80fd", "\ue8e8": "\u7ecf", "\ue760": "\u4f55", "\ue6f0": "\u4e66", "\ued27": "\u6837", "\ue259": "\u6709", "\ue1bf": "\u7b49", "\uede5": "\u6b7b", "\uea72": "\u5916", "\ue11e": "\u6ca1", "\uedef": "\u5206", "\ue4d5": "\u672c", "\ue210": "\u6c11", "\ue3d2": "\u5979", "\ue729": "\u6210", "\uef14": "\u4e48", "\ue11b": "\u7684", "\uefc7": "\u7f8e", "\ue1b1": "\u53f2", "\uec08": "\u4ee5", "\ue002": "\u88ab", "\ue900": "\u4e16", "\uea30": "\u5199", "\uecbe": "\u7b2c", "\ueeda": "\u4e9b", "\ue7b1": "\u4f46", "\ue716": "\u4e3b", "\ue9a9": "\u7406", "\ue042": "\u5973", "\uea73": "\u90fd", "\ue785": "\u793e", "\ue98b": "\u70b9", "\uec9e": "\u53bb", "\uefad": "\u529b", "\ue3c0": "\u5982", "\ue03c": "\u66f4", "\ue554": "\u7279", "\ue667": "\u767d", "\ue2d2": "\u6240", "\uea9d": "\u5176", "\uea68": "\u4e8c", "\ue572": "\u610f", "\ue2c7": "\u611f", "\ue591": "\u8001", "\ue6c4": "\u81ea", "\uefec": "\u56db", "\ue3d5": "\u4f60", "\uea7b": "\u8bdd", "\ue322": "\u53ea", "\uea3f": "\u4e49", "\ue0e6": "\u4e2d", "\ue2fe": "\u7531", "\ueb0d": "\u56fd", "\ue91a": "\u548c", "\ue5f6": "\u5bb6", "\ue992": "\u95f4", "\ue952": "\u53c8", "\ueb80": "\u800c", "\ue74d": "\u660e", "\ue6fd": "\u592a", "\uef68": "\u4e0e", "\ue64f": "\u4e5f", "\ueb95": "\u5148", "\uee8c": "\u770b", "\uece0": "\u4e24", "\ue172": "\u60c5", "\ue892": "\u4e8b", "\ue731": "\u5c0f", "\ue053": "\u5b83", "\ue98e": "\u597d", "\ue085": "\u4f1a", "\ue279": "\u4e0a", "\ue4cc": "\u4e09"}