{"\ue1b4": "\u65e0", "\ue6ff": "\u8d77", "\uef46": "\u6765", "\ue354": "\u8d70", "\ue817": "\u8fd8", "\ue30a": "\u66f4", "\ue491": "\u751f", "\ue67b": "\u6b7b", "\ue8e1": "\u4ed6", "\ue97a": "\u611f", "\ued39": "\u5bb6", "\uebf5": "\u6b64", "\uef7a": "\u5bf9", "\ueda9": "\u5f88", "\ue12a": "\u8bba", "\uea90": "\u6837", "\ueecc": "\u4fbf", "\ue3a9": "\u5f53", "\ue0ca": "\u672c", "\ue64f": "\u516c", "\uef6e": "\u5316", "\ue590": "\u5b50", "\uec19": "\u56e0", "\uee67": "\u7f8e", "\ue7f6": "\u4eba", "\ue33b": "\u5c31", "\ue7f1": "\u5b66", "\ueabd": "\u7ed9", "\uef01": "\u5374", "\ue037": "\u4eec", "\ue80b": "\u6240", "\ue62e": "\u65b0", "\ueb22": "\u7406", "\ue52e": "\u4e3b", "\ue972": "\u9762", "\ue1dd": "\u884c", "\ue4a3": "\u4ee5", "\ue96e": "\u624b", "\uec4d": "\u91cd", "\uea34": "\u76f8", "\ue056": "\u90e8", "\ue615": "\u95e8", "\ueae5": "\u5173", "\uea84": "\u53d1", "\ue0c0": "\u4e8c", "\uec6b": "\u5916", "\uecef": "\u6027", "\ued8b": "\u5168", "\uee9b": "\u4e4b", "\ue13c": "\u53f2", "\ue4b1": "\u56de", "\ue75b": "\u53bb", "\uee4d": "\u957f", "\ue696": "\u56fd", "\uea5e": "\u52a8", "\uee87": "\u5c11", "\ue6dc": "\u800c", "\uee97": "\u6210", "\ue3f7": "\u4e9b", "\ue93b": "\u5148", "\ueba6": "\u65f6", "\ue74b": "\u6700", "\ue411": "\u4e5f", "\ued34": "\u4e86", "\ue377": "\u7684", "\ueb3d": "\u51e0", "\ue596": "\u8fdb", "\ue9c1": "\u4e0d", "\ue10a": "\u79cd", "\uef0e": "\u610f", "\uee43": "\u5f97", "\ue803": "\u540e", "\ueffa": "\u7279", "\ueb74": "\u773c", "\ue7cd": "\u5973", "\ue8ae": "\u592a", "\ue6e6": "\u6c11", "\ued08": "\u77e5", "\ue65c": "\u8bdd", "\ue0a6": "\u6587", "\ue201": "\u5730", "\ue2a6": "\u70b9", "\uef4e": "\u5934", "\ued2d": "\u4f53", "\ue0a3": "\u5f00", "\ue1dc": "\u6559", "\ue7cf": "\u5341", "\uee35": "\u5230", "\uef32": "\u6ca1", "\ue7aa": "\u5e76", "\uefb9": "\u5c0f", "\ue521": "\u8eab", "\ued78": "\u793e", "\uee8b": "\u91cc", "\ue06a": "\u8fd9", "\ue1fa": "\u60c5", "\uef2c": "\u7269", "\ue560": "\u7b49", "\ue394": "\u4e00", "\ue7c3": "\u5176", "\ueb5b": "\u5b83", "\ueee4": "\u53ef", "\ue944": "\u5982", "\ueae6": "\u7136", "\ue955": "\u5979", "\ue2f8": "\u5411", "\ue7eb": "\u624d", "\uea74": "\u95f4", "\ueb1f": "\u7528", "\ued69": "\u80fd", "\uef8e": "\u88ab", "\ue840": "\u4e49", "\ue3d7": "\u6211", "\ue3c3": "\u548c", "\ue0fc": "\u4e09", "\uea8b": "\u522b", "\ueed4": "\u4f60", "\ue95a": "\u5fc3", "\ue716": "\u65b9", "\ue1e5": "\u518d", "\ue981": "\u9053", "\ue482": "\u6c14", "\ued6b": "\u5b9e", "\uef3f": "\u7b11", "\ue810": "\u90fd", "\ue6ea": "\u51fa", "\uedb9": "\u770b", "\ueca3": "\u513f", "\ue122": "\u679c", "\ue7b1": "\u5728", "\ue1e1": "\u53c8", "\ue67e": "\u6b63", "\ue793": "\u524d", "\ue854": "\u601d", "\ue034": "\u56db", "\ue516": "\u5e74", "\ue61b": "\u53ea", "\ue7ba": "\u4e24", "\ueced": "\u591a", "\ue3a5": "\u767d", "\ue07c": "\u4f5c", "\ue46f": "\u5206", "\ue6c8": "\u4e0b", "\ueb98": "\u8981", "\ue20c": "\u4e0a", "\ue113": "\u4e0e", "\uee1b": "\u5c06", "\ueac4": "\u5df1", "\uee8a": "\u6709", "\uec1d": "\u4e2a", "\ueb6e": "\u8fc7", "\ue081": "\u53e3", "\ue9b0": "\u8bf4", "\uecc5": "\u4e3a", "\uec05": "\u542c", "\ue6be": "\u5929", "\ue444": "\u628a", "\ue533": "\u5199", "\ue1bf": "\u81ea", "\uea9d": "\u7ecf", "\ueebf": "\u660e", "\uead2": "\u662f", "\uebd7": "\u8001", "\ue5d1": "\u4f55", "\ue4de": "\u6253", "\ueb3e": "\u7531", "\ue830": "\u6cd5", "\ue78b": "\u7b2c", "\uead6": "\u4ee3", "\ueef2": "\u771f", "\ue076": "\u540d", "\uef26": "\u4ec0", "\uedba": "\u4e48", "\uecf4": "\u5b9a", "\uec67": "\u529b", "\ue22e": "\u4e2d", "\ue9bc": "\u4ece", "\ue06f": "\u7740", "\ue1a1": "\u65e5", "\ue2c9": "\u4e8e", "\uea98": "\u58f0", "\ue5ee": "\u5df2", "\ue5bb": "\u4f7f", "\ue6df": "\u4f46", "\ue842": "\u4e8b", "\ue28f": "\u4f1a", "\ue17c": "\u8005", "\ue042": "\u9ad8", "\ue1bd": "\u5927", "\ueba4": "\u795e", "\uec5f": "\u60f3", "\ue249": "\u4e66", "\ue806": "\u897f", "\uef9c": "\u4e16", "\ueff8": "\u597d", "\ue83f": "\u95ee", "\uee76": "\u89c1", "\ue710": "\u540c", "\uee07": "\u73b0", "\ue63c": "\u90a3"}