{"\uec88": "\u7269", "\uee2f": "\u548c", "\ue516": "\u5c0f", "\ue100": "\u8fd9", "\ue4b2": "\u65e5", "\ueb6e": "\u6210", "\ue328": "\u4f55", "\ue890": "\u884c", "\ued76": "\u5230", "\uee67": "\u65e0", "\ue759": "\u70b9", "\ue57d": "\u770b", "\ue8aa": "\u5148", "\ueb48": "\u4e8c", "\uebbd": "\u4e09", "\uef35": "\u4e0b", "\ue34f": "\u628a", "\ue94f": "\u7528", "\ue68b": "\u6587", "\ue27e": "\u56de", "\ue3b0": "\u4f5c", "\ue633": "\u51fa", "\ue49e": "\u91cc", "\uefdd": "\u4e66", "\uea38": "\u8fc7", "\ue8ec": "\u6b63", "\uefe6": "\u51e0", "\uefeb": "\u6b7b", "\uedce": "\u7ed9", "\uef8b": "\u624b", "\ue65a": "\u4ec0", "\ue298": "\u58f0", "\ue91c": "\u522b", "\uec05": "\u679c", "\ueaea": "\u5b9a", "\uefe0": "\u7136", "\ue113": "\u793e", "\uee9d": "\u5316", "\uea98": "\u7684", "\ue49f": "\u95e8", "\ue83d": "\u5fc3", "\ue39b": "\u4f1a", "\ue23e": "\u4e0e", "\ueb0f": "\u9053", "\ue9a6": "\u5f00", "\ue715": "\u662f", "\uedd9": "\u751f", "\uecbb": "\u597d", "\ue122": "\u4eba", "\ue1bd": "\u5f97", "\ue8a6": "\u601d", "\uea62": "\u5341", "\ue66e": "\u4e3b", "\ue47a": "\u9762", "\uef92": "\u660e", "\ueff4": "\u7531", "\ue932": "\u5730", "\ued0a": "\u56fd", "\ue3db": "\u8bba", "\ueb3c": "\u5973", "\ue558": "\u5916", "\ue116": "\u7740", "\ue91e": "\u6cd5", "\ue45f": "\u6837", "\ue0d2": "\u6211", "\ue985": "\u66f4", "\ued57": "\u5173", "\uec65": "\u79cd", "\ue371": "\u9ad8", "\uefa8": "\u4e8e", "\ue44f": "\u5728", "\ue821": "\u53d1", "\ue06e": "\u56e0", "\ue05c": "\u540c", "\uebf4": "\u88ab", "\ue548": "\u4e2a", "\ue9c6": "\u529b", "\ue094": "\u4e2d", "\ue3a8": "\u4e16", "\ue5c8": "\u4f53", "\ue0b0": "\u4e4b", "\uefa6": "\u767d", "\ue049": "\u5c31", "\ue8e5": "\u7279", "\ueb4f": "\u6c11", "\uea74": "\u5b9e", "\ue6b2": "\u5979", "\uedf1": "\u5c11", "\ue9e7": "\u5206", "\ue051": "\u5b66", "\ue680": "\u95f4", "\uec00": "\u90a3", "\ued53": "\u624d", "\ued1e": "\u4e3a", "\uef66": "\u5e74", "\ueea0": "\u4ee5", "\ueea8": "\u4e0d", "\uefaa": "\u897f", "\uea6e": "\u8d77", "\ue0e3": "\u672c", "\ue0ed": "\u53bb", "\ue286": "\u6c14", "\ue071": "\u611f", "\ue375": "\u5927", "\ue754": "\u771f", "\ue9b9": "\u53ef", "\ue2bb": "\u4ee3", "\ue36c": "\u8001", "\ue16a": "\u5b83", "\ue181": "\u81ea", "\ue031": "\u518d", "\ue26b": "\u4e48", "\ue397": "\u524d", "\uec99": "\u7b2c", "\uee22": "\u5168", "\uecb0": "\u95ee", "\uec2c": "\u540e", "\ued2c": "\u8eab", "\uedc1": "\u6027", "\ue5f2": "\u5411", "\ue9d0": "\u4e86", "\ue1e0": "\u7b49", "\ue704": "\u5982", "\ue0fa": "\u7b11", "\uece9": "\u4e5f", "\uee7e": "\u5934", "\ue6cb": "\u542c", "\ue02f": "\u5df1", "\ue6ed": "\u4f46", "\ue43b": "\u7f8e", "\uecd2": "\u4f60", "\ue288": "\u5df2", "\ue7a3": "\u4fbf", "\ue115": "\u53c8", "\ue63b": "\u6765", "\ue846": "\u6240", "\uefaf": "\u5374", "\ue6c6": "\u56db", "\ue059": "\u91cd", "\ue258": "\u53e3", "\ue4e4": "\u6b64", "\uee1b": "\u773c", "\ued21": "\u60c5", "\ue52f": "\u8981", "\uea8c": "\u5c06", "\ue53f": "\u6ca1", "\uef3b": "\u800c", "\ue4ab": "\u957f", "\uebca": "\u4e8b", "\ued88": "\u6700", "\ue66b": "\u7ecf", "\ue158": "\u591a", "\ueeb3": "\u6709", "\ue665": "\u5f53", "\ue784": "\u77e5", "\uedb4": "\u513f", "\ueb2d": "\u52a8", "\ue00d": "\u4e9b", "\ued4b": "\u5b50", "\ue3ee": "\u610f", "\uebc1": "\u90e8", "\ue344": "\u4ed6", "\ue5f4": "\u80fd", "\ue9ae": "\u8fdb", "\uea23": "\u8fd8", "\ue376": "\u90fd", "\ue067": "\u4e24", "\uee53": "\u516c", "\ue825": "\u7406", "\ue965": "\u592a", "\ue805": "\u5f88", "\ue5d7": "\u5199", "\ue0f4": "\u53ea", "\ue904": "\u89c1", "\uedbf": "\u5e76", "\ue6b1": "\u5bb6", "\ue436": "\u4f7f", "\ue224": "\u65f6", "\ue84a": "\u8bdd", "\ue94d": "\u540d", "\ue743": "\u65b9", "\uec4b": "\u4eec", "\ue894": "\u6559", "\ue636": "\u8bf4", "\ued2b": "\u8d70", "\uef00": "\u73b0", "\ueff6": "\u5176", "\ue168": "\u4e49", "\ue1d9": "\u65b0", "\ue4a8": "\u53f2", "\ue982": "\u4ece", "\ue563": "\u5929", "\ue335": "\u8005", "\ue2f5": "\u6253", "\ue0c1": "\u4e0a", "\ue218": "\u4e00", "\ue6fa": "\u5bf9", "\ue59e": "\u60f3", "\uebbf": "\u76f8", "\ue21e": "\u795e"}