{"\ueced": "\u7279", "\uef6c": "\u5929", "\ue835": "\u7136", "\uec9a": "\u4f5c", "\ued81": "\u4e3b", "\ueca3": "\u7531", "\ue9c7": "\u6709", "\ue5b1": "\u542c", "\uef6b": "\u8005", "\ue6de": "\u800c", "\ue811": "\u540d", "\ue687": "\u6240", "\uef66": "\u56de", "\ue501": "\u65b9", "\ueec6": "\u7f8e", "\ue5eb": "\u5df2", "\ue207": "\u5b9e", "\uea19": "\u597d", "\ue5b9": "\u751f", "\ue00a": "\u8001", "\ue911": "\u5b66", "\ue9ab": "\u5e74", "\ue247": "\u9053", "\ueb33": "\u60f3", "\uee6b": "\u773c", "\ue3de": "\u5c11", "\uea0a": "\u4e66", "\uef5a": "\u5b83", "\ue5ef": "\u591a", "\ue734": "\u65e5", "\ue7a7": "\u4f7f", "\ueb18": "\u6700", "\ue596": "\u540e", "\ue1b9": "\u5e76", "\uedd7": "\u91cc", "\ue2b1": "\u53f2", "\ue52f": "\u6559", "\ue604": "\u5316", "\ue1d5": "\u660e", "\ue9e2": "\u529b", "\ue561": "\u611f", "\ueaee": "\u9762", "\ued0c": "\u4f1a", "\ue1cc": "\u4ed6", "\ue1d9": "\u6837", "\ue697": "\u4e0b", "\uebc4": "\u6027", "\ue93a": "\u7269", "\ue42a": "\u4eba", "\ue56e": "\u4ee3", "\uef08": "\u8bba", "\ue71c": "\u7740", "\uea87": "\u56e0", "\ue022": "\u73b0", "\ue28e": "\u8d70", "\ue210": "\u770b", "\uea5e": "\u5199", "\ue8e4": "\u8bf4", "\ue794": "\u5fc3", "\ue95c": "\u897f", "\ue16b": "\u65b0", "\uec96": "\u56db", "\ue5c4": "\u6b64", "\ueb64": "\u5927", "\ue9c3": "\u7b11", "\ue83e": "\u5916", "\ued58": "\u8fd8", "\uea0c": "\u66f4", "\ue84f": "\u56fd", "\ue165": "\u4e00", "\ue7ad": "\u89c1", "\ue421": "\u4e09", "\ue6c4": "\u95f4", "\ue47f": "\u90a3", "\uec30": "\u6b7b", "\ue0a9": "\u4e49", "\uec9e": "\u6c14", "\ue03e": "\u672c", "\ue8f3": "\u524d", "\uef05": "\u4f46", "\ue9b1": "\u58f0", "\ueb59": "\u88ab", "\ue0fb": "\u4e3a", "\ue33b": "\u4e0a", "\ue52b": "\u767d", "\ue5a9": "\u957f", "\ue105": "\u601d", "\uebc7": "\u7528", "\ue9da": "\u70b9", "\uea1a": "\u4e16", "\ue350": "\u95e8", "\uee6a": "\u5bb6", "\uec71": "\u513f", "\ue7a9": "\u771f", "\ued57": "\u5f97", "\ue5cc": "\u8fc7", "\ue7c3": "\u6cd5", "\ue194": "\u5728", "\ue142": "\u516c", "\ue622": "\u518d", "\uee41": "\u793e", "\ue38e": "\u592a", "\ued26": "\u6c11", "\ueac4": "\u4e5f", "\ue08d": "\u7b49", "\ue85f": "\u4e86", "\uef68": "\u80fd", "\ue2b9": "\u76f8", "\ue19a": "\u51fa", "\ued17": "\u6765", "\ue251": "\u5b50", "\uec9b": "\u5c06", "\ue280": "\u624b", "\ue4dd": "\u6b63", "\ue588": "\u7ed9", "\ue9ed": "\u4e8c", "\ue77f": "\u4ee5", "\uea4d": "\u5730", "\ue62d": "\u81ea", "\ue636": "\u5f88", "\ue172": "\u5973", "\ue0c1": "\u795e", "\ue8ad": "\u7684", "\uedae": "\u884c", "\uefbd": "\u4e8e", "\uebe1": "\u5411", "\ue527": "\u5934", "\ue679": "\u4e2d", "\ue582": "\u548c", "\uebf7": "\u4e8b", "\ue2cd": "\u6ca1", "\ue43e": "\u6210", "\ued59": "\u7406", "\uea2d": "\u53bb", "\ue329": "\u5148", "\ue851": "\u5f53", "\ue6e1": "\u4ec0", "\uee8e": "\u4e48", "\ue871": "\u5b9a", "\ue0cd": "\u8981", "\ue4d6": "\u4e0d", "\ue90a": "\u65f6", "\ue6a4": "\u4f55", "\ue01b": "\u4ece", "\uea1b": "\u5982", "\uea57": "\u79cd", "\ueb0a": "\u522b", "\ue6a7": "\u540c", "\uee33": "\u662f", "\ue553": "\u5bf9", "\ue09b": "\u53ef", "\ue9bb": "\u610f", "\ueddd": "\u5df1", "\ue2d6": "\u4fbf", "\ue0f0": "\u95ee", "\ued70": "\u8fdb", "\uef04": "\u5f00", "\ue9af": "\u51e0", "\ue9ef": "\u679c", "\ueb6a": "\u53ea", "\uedef": "\u4e4b", "\ue113": "\u91cd", "\uea42": "\u624d", "\ueb69": "\u6211", "\uefbc": "\u5341", "\ue381": "\u5c31", "\ueed0": "\u4e2a", "\uedf4": "\u90e8", "\ue659": "\u5206", "\uefcc": "\u4f60", "\ue1e7": "\u9ad8", "\ue3c8": "\u5979", "\ued68": "\u5176", "\ue50b": "\u8eab", "\ueae6": "\u7ecf", "\ueff1": "\u53e3", "\ue825": "\u4e0e", "\ueb56": "\u52a8", "\ueaba": "\u53d1", "\ue610": "\u8fd9", "\ue05d": "\u53c8", "\ued23": "\u60c5", "\ue91d": "\u7b2c", "\ue695": "\u6253", "\ue8ea": "\u90fd", "\ue4a0": "\u8d77", "\ue0ca": "\u8bdd", "\ue0dc": "\u5230", "\ue9a1": "\u65e0", "\ue637": "\u4e24", "\ue56b": "\u6587", "\ue4b2": "\u5374", "\ue5c8": "\u5168", "\ue681": "\u4eec", "\uee7c": "\u77e5", "\ue9c6": "\u628a", "\ued71": "\u4f53", "\uef50": "\u5c0f", "\ue63b": "\u5173", "\ue839": "\u4e9b"}