{"\ue054": "\u80fd", "\uede8": "\u8d77", "\uee55": "\u6c14", "\ue4cb": "\u4e09", "\ue728": "\u8eab", "\ue3f7": "\u5728", "\ue189": "\u7740", "\ue3cb": "\u91cc", "\ue34b": "\u5173", "\uef09": "\u4e5f", "\ue012": "\u800c", "\ue1af": "\u6ca1", "\uec02": "\u524d", "\ue2cb": "\u5f53", "\ue949": "\u8bf4", "\ue5d7": "\u5973", "\uebf3": "\u660e", "\ue254": "\u51fa", "\ue291": "\u8fd9", "\ue5ff": "\u76f8", "\ue7f3": "\u4eec", "\ue1c0": "\u5c11", "\uea19": "\u4e24", "\uef47": "\u884c", "\ue54d": "\u4e86", "\ue643": "\u5bb6", "\ue9e0": "\u5230", "\ue0ae": "\u628a", "\ue952": "\u91cd", "\uea1e": "\u793e", "\uec9b": "\u7269", "\ueb70": "\u5176", "\ue6d7": "\u56de", "\ue33f": "\u4e48", "\ue5c4": "\u770b", "\ue710": "\u597d", "\ued31": "\u5df2", "\ue558": "\u4e2a", "\uecd5": "\u65b0", "\uefe9": "\u4ed6", "\ue1ad": "\u4f53", "\ue3a0": "\u9762", "\uee30": "\u4ee3", "\uee45": "\u4f7f", "\ue793": "\u529b", "\ue01e": "\u6765", "\ue8d1": "\u6b64", "\uee99": "\u73b0", "\uef96": "\u53e3", "\ueb1d": "\u601d", "\ue110": "\u53f2", "\ue9b3": "\u4e4b", "\ue08c": "\u591a", "\ue60f": "\u4e0e", "\ue6c9": "\u4e3a", "\ue8a0": "\u773c", "\uebe9": "\u7f8e", "\ue84e": "\u8bdd", "\ueca5": "\u56db", "\ue6bc": "\u8fdb", "\ue719": "\u5bf9", "\ue682": "\u679c", "\ue417": "\u90fd", "\ue5e9": "\u610f", "\ue781": "\u4e9b", "\uef9c": "\u8d70", "\ue49a": "\u624d", "\ue419": "\u5199", "\ued21": "\u957f", "\uefc8": "\u5929", "\ue0a6": "\u51e0", "\ue2b6": "\u56e0", "\ue99b": "\u7ed9", "\ueac0": "\u6211", "\uee2c": "\u6240", "\ue172": "\u4fbf", "\ue861": "\u60c5", "\ueb22": "\u5e76", "\ued70": "\u8fd8", "\uea71": "\u540d", "\ue752": "\u89c1", "\uee7b": "\u4e00", "\ue67b": "\u542c", "\ue108": "\u7528", "\uea47": "\u4e0b", "\ue541": "\u8005", "\ueb92": "\u5411", "\ue310": "\u6700", "\ue457": "\u95e8", "\ue886": "\u95f4", "\ue633": "\u56fd", "\ue795": "\u662f", "\ueb51": "\u7b2c", "\uebab": "\u795e", "\uebdd": "\u88ab", "\uea25": "\u592a", "\ue0de": "\u5b66", "\ue132": "\u6c11", "\ue216": "\u5c06", "\ue989": "\u5934", "\ueb33": "\u5b9e", "\ueb63": "\u5c0f", "\ue157": "\u548c", "\uefea": "\u79cd", "\uead7": "\u7406", "\ue320": "\u5979", "\ue10a": "\u4eba", "\ue351": "\u4e8c", "\ue3bb": "\u4e0d", "\uef11": "\u7279", "\uefba": "\u5b9a", "\ue050": "\u5341", "\ue07f": "\u672c", "\ue2ab": "\u6210", "\ue2d2": "\u5916", "\ue411": "\u53c8", "\ue44d": "\u611f", "\ue6e9": "\u4e49", "\ued87": "\u4e0a", "\ued1f": "\u522b", "\uefb3": "\u60f3", "\ue607": "\u624b", "\ueac4": "\u5316", "\uebd5": "\u5927", "\ueaf0": "\u53bb", "\ue3eb": "\u58f0", "\ue104": "\u6709", "\uea92": "\u77e5", "\uecc3": "\u5fc3", "\ue1f5": "\u65e0", "\ue129": "\u9ad8", "\uee3d": "\u53ea", "\ue852": "\u5c31", "\ue7bf": "\u4ece", "\ue3cc": "\u4ec0", "\ue9d2": "\u7b11", "\ue70e": "\u6b7b", "\uec0c": "\u52a8", "\ueeb0": "\u9053", "\uec12": "\u513f", "\uee34": "\u7b49", "\ue6bf": "\u6559", "\ued09": "\u53d1", "\ue161": "\u6027", "\ue6ef": "\u6cd5", "\ue24f": "\u5e74", "\uec73": "\u4e3b", "\ue50c": "\u6b63", "\ue70c": "\u7684", "\ue6a8": "\u5730", "\ue95c": "\u5f00", "\ue1f1": "\u53ef", "\ue9d8": "\u6253", "\uebc7": "\u4e16", "\uec1a": "\u81ea", "\ue5ac": "\u6837", "\ue534": "\u4e8b", "\uea31": "\u751f", "\ue8d5": "\u65b9", "\ued71": "\u5df1", "\ue6a2": "\u90a3", "\ueacb": "\u8bba", "\uea9a": "\u8001", "\ue9bc": "\u767d", "\uec79": "\u6587", "\uee83": "\u4f46", "\ue995": "\u66f4", "\ue798": "\u5f97", "\uee5a": "\u7531", "\ue4e6": "\u5168", "\uec41": "\u4e8e", "\ue2af": "\u65f6", "\ue61d": "\u4ee5", "\ue73f": "\u4e66", "\uefb7": "\u4e2d", "\uea07": "\u4f1a", "\ueda4": "\u4f60", "\uec74": "\u4f5c", "\ue551": "\u518d", "\uee37": "\u5b83", "\ue6e8": "\u8981", "\uef74": "\u5206", "\ue0e4": "\u90e8", "\uea26": "\u5f88", "\ue631": "\u7136", "\uede0": "\u70b9", "\ue69a": "\u4f55", "\ue933": "\u897f", "\ue438": "\u540c", "\ued1c": "\u5982", "\ue63c": "\u5b50", "\ue9cd": "\u5148", "\uedd1": "\u7ecf", "\ue93c": "\u95ee", "\ue398": "\u516c", "\ue8a8": "\u5374", "\ue79a": "\u8fc7", "\ue405": "\u771f", "\uebcb": "\u540e", "\ue0b0": "\u65e5"}