{"\ueabd": "\u65f6", "\ueac9": "\u4e8b", "\ue8f5": "\u5728", "\ue8dc": "\u5e76", "\uede9": "\u5df2", "\uef45": "\u4e09", "\uee4b": "\u4e16", "\ue71b": "\u540d", "\ue9ec": "\u5b83", "\ue8bb": "\u540c", "\ued68": "\u88ab", "\uee56": "\u5c31", "\ue956": "\u9ad8", "\ue324": "\u4e9b", "\ue8e8": "\u6587", "\uea07": "\u4e0e", "\ue8a8": "\u8001", "\ueb95": "\u4ee3", "\ue260": "\u8d77", "\ue21a": "\u5c0f", "\uec70": "\u5173", "\ue0e6": "\u524d", "\ue973": "\u5411", "\uea0e": "\u5df1", "\ue04b": "\u53bb", "\ue4ad": "\u6c11", "\ueeef": "\u591a", "\ue426": "\u53e3", "\ue4ed": "\u58f0", "\ue999": "\u4e0d", "\uebc8": "\u5199", "\uea95": "\u624d", "\uedb9": "\u4e48", "\ueef9": "\u76f8", "\ue108": "\u70b9", "\ue2bb": "\u65e0", "\ue2a0": "\u95ee", "\uee4a": "\u7b11", "\ue966": "\u884c", "\ueaff": "\u4f55", "\ueaf3": "\u516c", "\ue190": "\u897f", "\ue57d": "\u767d", "\ue611": "\u4e8e", "\ue00e": "\u529b", "\ue163": "\u5c11", "\ue1fb": "\u53f2", "\ue3a5": "\u81ea", "\uef33": "\u4f46", "\uef68": "\u5f88", "\ue112": "\u5168", "\uec06": "\u4f53", "\ue6e4": "\u6709", "\ue9e5": "\u7ecf", "\ue559": "\u4f60", "\ue830": "\u95f4", "\ue82a": "\u53ea", "\ue4e2": "\u6240", "\ue0d1": "\u4e4b", "\ue3e6": "\u51fa", "\ue875": "\u4eba", "\ue634": "\u5916", "\ue7df": "\u7528", "\ue5a2": "\u5f97", "\ue441": "\u56e0", "\ue01c": "\u601d", "\ueb22": "\u795e", "\ue256": "\u4e5f", "\ue51a": "\u8005", "\ue821": "\u771f", "\ue930": "\u9762", "\uec92": "\u7136", "\uebca": "\u4fbf", "\ue306": "\u5b9a", "\uea97": "\u6cd5", "\ue576": "\u5b50", "\ue98a": "\u540e", "\ue4c7": "\u56de", "\ue910": "\u793e", "\uefae": "\u6b7b", "\ue111": "\u7406", "\ue133": "\u518d", "\ue545": "\u8eab", "\uec8c": "\u8981", "\ue6c5": "\u5341", "\ued5f": "\u8fc7", "\ue8a1": "\u542c", "\ueafc": "\u8fd9", "\ueaa2": "\u80fd", "\ue53f": "\u628a", "\ue528": "\u610f", "\uee30": "\u8fdb", "\uef94": "\u7ed9", "\ue7ab": "\u6837", "\ue998": "\u597d", "\ue2fd": "\u90fd", "\ue445": "\u957f", "\ue0ff": "\u592a", "\ue2a5": "\u90a3", "\ue583": "\u8bf4", "\ue647": "\u611f", "\uecfc": "\u5374", "\ue29f": "\u6ca1", "\ue16f": "\u5bf9", "\ue7d7": "\u4ec0", "\ue3a1": "\u5bb6", "\uec5d": "\u66f4", "\ue21d": "\u56db", "\ue541": "\u770b", "\ue862": "\u773c", "\ue0d0": "\u7279", "\uedf5": "\u5230", "\uee04": "\u6211", "\ue1a4": "\u5927", "\ue832": "\u5b66", "\ue679": "\u672c", "\uec40": "\u60c5", "\ue713": "\u60f3", "\ued40": "\u6027", "\ue280": "\u660e", "\ue8eb": "\u4f1a", "\uedae": "\u7f8e", "\ue0b1": "\u8fd8", "\ued81": "\u95e8", "\ue041": "\u5206", "\ue64c": "\u4e8c", "\ue1f5": "\u5f00", "\ue433": "\u4e86", "\ued8e": "\u624b", "\ueb9e": "\u4e66", "\ue79a": "\u5934", "\uec84": "\u5176", "\ue104": "\u7b49", "\uef03": "\u53c8", "\ueb1f": "\u5148", "\uec19": "\u53ef", "\ue457": "\u6700", "\uef5d": "\u4e2a", "\ue46f": "\u89c1", "\ue55c": "\u800c", "\ue731": "\u6210", "\ueff6": "\u4ece", "\ueec8": "\u52a8", "\uee17": "\u662f", "\ue316": "\u4e0b", "\ueea4": "\u6253", "\uec3a": "\u548c", "\ue85c": "\u77e5", "\ue017": "\u6b64", "\ue30c": "\u8bdd", "\ue3c2": "\u8bba", "\ue2ca": "\u4e49", "\uea49": "\u91cd", "\ue8da": "\u51e0", "\uecd6": "\u7740", "\ue891": "\u56fd", "\ue71c": "\u4e00", "\ue84a": "\u4e3b", "\uefc9": "\u6b63", "\ueff3": "\u5c06", "\ueb5f": "\u7b2c", "\ue7e5": "\u4e0a", "\ue970": "\u4e24", "\ue15b": "\u4f7f", "\ue9f8": "\u5b9e", "\ue3ab": "\u4e3a", "\ue4ac": "\u5f53", "\ue595": "\u7531", "\ue12f": "\u4ed6", "\ue8db": "\u65b9", "\uea5a": "\u73b0", "\uef65": "\u4ee5", "\uefaf": "\u513f", "\ue64a": "\u8d70", "\uee65": "\u5730", "\ued58": "\u6c14", "\ue82e": "\u5973", "\uecb0": "\u4eec", "\ue11f": "\u79cd", "\ue75f": "\u4e2d", "\ue0c6": "\u4f5c", "\ue119": "\u6765", "\ue149": "\u65e5", "\ue7f9": "\u5fc3", "\uee2c": "\u65b0", "\ue1fa": "\u6559", "\uea05": "\u90e8", "\ue801": "\u751f", "\ueab9": "\u5316", "\ueb30": "\u7269", "\uec37": "\u5929", "\uee0a": "\u7684", "\ue1c8": "\u5979", "\ue59d": "\u5982", "\ue64e": "\u679c", "\uee66": "\u522b", "\ue70f": "\u53d1", "\uef74": "\u5e74", "\ue06c": "\u91cc", "\ueeee": "\u9053"}