{"\uea9f": "\u8001", "\ue07d": "\u5341", "\uebc3": "\u5929", "\ue5dc": "\u6210", "\uef67": "\u7406", "\ueef0": "\u4ee5", "\ue5a6": "\u95ee", "\ue39b": "\u5374", "\ue02b": "\u6700", "\ue82f": "\u6253", "\ued1c": "\u4e09", "\uedd5": "\u5230", "\ueed5": "\u4e0b", "\uecd9": "\u53ea", "\ue688": "\u5df1", "\uee60": "\u4e8e", "\ueff2": "\u53bb", "\ue840": "\u542c", "\ue63a": "\u4e0d", "\ue4a4": "\u6027", "\ueb45": "\u8fd8", "\uec29": "\u610f", "\ue1eb": "\u65b0", "\ue90a": "\u81ea", "\ue188": "\u5979", "\uef24": "\u4e3a", "\uef7e": "\u4e00", "\ue5c8": "\u4e48", "\ueab8": "\u884c", "\uec41": "\u4f7f", "\ue8da": "\u4e8b", "\uea28": "\u65f6", "\ueae4": "\u5b9e", "\ue0f8": "\u4e24", "\ue599": "\u4e0a", "\ueb60": "\u5316", "\ue16c": "\u4e49", "\uedb2": "\u4f53", "\ueaab": "\u6587", "\uebdf": "\u90e8", "\ue01a": "\u56fd", "\uea40": "\u4e16", "\ue99a": "\u4e2a", "\ue841": "\u4f1a", "\uefcd": "\u6240", "\ue59e": "\u5c11", "\ue653": "\u4e3b", "\uee16": "\u60f3", "\ue089": "\u5973", "\ue32f": "\u5206", "\ueda6": "\u660e", "\uef4a": "\u4ece", "\ue6c8": "\u9ad8", "\ue61c": "\u957f", "\ue21e": "\u897f", "\ue154": "\u8eab", "\uedf2": "\u80fd", "\ue20e": "\u591a", "\ue4fe": "\u6cd5", "\ue304": "\u9762", "\uef10": "\u4e66", "\ueb8a": "\u6b7b", "\uef52": "\u4f55", "\ue119": "\u5f97", "\uecd0": "\u4e9b", "\uef3c": "\u6559", "\ue3b6": "\u90a3", "\ued4b": "\u4f46", "\ued3b": "\u6ca1", "\uef41": "\u6b63", "\ue11a": "\u6837", "\ue0f5": "\u77e5", "\ue888": "\u5c06", "\ued30": "\u53c8", "\ueb44": "\u529b", "\ue9a8": "\u53d1", "\ue57d": "\u51fa", "\ue84a": "\u95f4", "\ue721": "\u5916", "\ue932": "\u4f5c", "\uec66": "\u5e76", "\ued6f": "\u5f88", "\ue28f": "\u5148", "\ueae8": "\u8bdd", "\uef81": "\u5b50", "\ue12b": "\u5b83", "\ue0f6": "\u4e0e", "\ue395": "\u5f00", "\ue3ae": "\u65e0", "\ue079": "\u5bf9", "\ue66c": "\u4ee3", "\ued58": "\u91cc", "\ue5f6": "\u540e", "\ue097": "\u6c11", "\ue592": "\u53f2", "\ue031": "\u4e8c", "\ue512": "\u4ed6", "\ue362": "\u8fc7", "\ueb95": "\u51e0", "\uec7c": "\u8bba", "\ue38c": "\u4e5f", "\ue4c4": "\u800c", "\uec2f": "\u5bb6", "\ue4d8": "\u79cd", "\uece1": "\u7269", "\ue9a1": "\u5fc3", "\uea96": "\u5df2", "\ue936": "\u4f60", "\ue06c": "\u611f", "\ue4a0": "\u513f", "\ue7f2": "\u65e5", "\ue825": "\u592a", "\ue72d": "\u4ec0", "\ueecb": "\u65b9", "\ue937": "\u5176", "\ued8c": "\u751f", "\ue7e0": "\u8d77", "\ue0ff": "\u4e86", "\ue10d": "\u522b", "\uef72": "\u524d", "\ue01c": "\u540d", "\ue50d": "\u58f0", "\ue5eb": "\u773c", "\ueb27": "\u795e", "\ue06b": "\u770b", "\ue203": "\u5411", "\ue0bb": "\u5f53", "\ue3ac": "\u7531", "\ue3ef": "\u9053", "\uedd3": "\u6c14", "\ue2f4": "\u5b66", "\ue0c3": "\u628a", "\ue566": "\u516c", "\ue759": "\u7ecf", "\ueac4": "\u540c", "\ueb3a": "\u8981", "\uece4": "\u6211", "\ue357": "\u8d70", "\ue924": "\u7279", "\ued23": "\u7ed9", "\ue0f3": "\u89c1", "\ue760": "\u90fd", "\uec23": "\u52a8", "\ueff1": "\u4fbf", "\ue508": "\u679c", "\ue886": "\u624d", "\uef85": "\u91cd", "\ue17d": "\u56db", "\uea2d": "\u70b9", "\ueb08": "\u767d", "\ue819": "\u4eba", "\uea13": "\u597d", "\ue54d": "\u7b49", "\ue4b5": "\u7740", "\ue14e": "\u5199", "\ueed1": "\u5168", "\uef66": "\u4e2d", "\ued03": "\u7b11", "\ue1fe": "\u4eec", "\ue488": "\u5728", "\ue7d9": "\u5730", "\ueee5": "\u4e4b", "\uebe4": "\u624b", "\ued09": "\u6b64", "\uea8d": "\u8fd9", "\ue2cb": "\u771f", "\ue349": "\u6709", "\ue17b": "\u548c", "\ue46e": "\u793e", "\ue3f2": "\u53e3", "\ue4d0": "\u8005", "\ue287": "\u95e8", "\uef86": "\u56de", "\uef9c": "\u5b9a", "\uef1c": "\u53ef", "\ueaf0": "\u5173", "\ue52e": "\u7528", "\ueb81": "\u60c5", "\ue85a": "\u5934", "\ue102": "\u601d", "\uea9e": "\u5c31", "\ue94d": "\u518d", "\ue52a": "\u5c0f", "\ue345": "\u6765", "\ueb7f": "\u7b2c", "\uec1a": "\u76f8", "\uec5f": "\u7f8e", "\ue5f2": "\u5927", "\ue09a": "\u672c", "\ueaf7": "\u5982", "\ue50e": "\u7136", "\ue8fb": "\u66f4", "\ue899": "\u8bf4", "\ue14f": "\u5e74", "\ue05c": "\u73b0", "\ue882": "\u7684", "\ued0f": "\u662f", "\ue09d": "\u88ab", "\ue91f": "\u8fdb", "\ueafa": "\u56e0"}