{"\ue614": "\u81ea", "\uef2b": "\u8fd9", "\uede9": "\u884c", "\ue4e0": "\u5199", "\uec79": "\u53ef", "\uef45": "\u58f0", "\ue6ff": "\u5e74", "\uefc2": "\u5176", "\ue93f": "\u6c11", "\uef6e": "\u4e0b", "\ue17f": "\u53bb", "\ue6ea": "\u73b0", "\ue03d": "\u5316", "\ue073": "\u4e09", "\ue292": "\u4e24", "\uefc3": "\u52a8", "\ue3eb": "\u5927", "\uea4a": "\u4e00", "\ue857": "\u597d", "\uebed": "\u513f", "\uea66": "\u592a", "\ue076": "\u5374", "\uec4f": "\u8fd8", "\uedef": "\u540d", "\uef9d": "\u4e0d", "\ueb1a": "\u529b", "\ueacf": "\u5982", "\ue110": "\u53e3", "\uead9": "\u4e2a", "\uece2": "\u95ee", "\ue27d": "\u4f7f", "\uec3c": "\u4fbf", "\ued7f": "\u6c14", "\ue3b9": "\u4e2d", "\ue5e8": "\u5b50", "\ue762": "\u60f3", "\ueda9": "\u5979", "\uec74": "\u624b", "\ue909": "\u6211", "\ue02b": "\u5c11", "\ue5e4": "\u4e3a", "\ue37d": "\u5c06", "\ue402": "\u8fc7", "\uef47": "\u7b2c", "\uef50": "\u5b9e", "\uefe9": "\u66f4", "\ue3f0": "\u65f6", "\ue284": "\u4f55", "\uea35": "\u7ed9", "\ue3e5": "\u6765", "\ue23c": "\u9053", "\uefba": "\u65e5", "\ue163": "\u5730", "\ue49f": "\u80fd", "\ue8fd": "\u8d70", "\ueb5e": "\u4e8c", "\uebf3": "\u51fa", "\ue951": "\u4e86", "\ue121": "\u7b11", "\uee1f": "\u611f", "\ue33c": "\u90fd", "\ue3ac": "\u7740", "\ue626": "\u6ca1", "\ue593": "\u5c0f", "\ue48b": "\u795e", "\ueb64": "\u8001", "\ue1f7": "\u6240", "\uec21": "\u53f2", "\ueafd": "\u773c", "\uec6f": "\u7531", "\ue5c6": "\u6559", "\ue524": "\u6b64", "\ue691": "\u4e5f", "\ue158": "\u7279", "\ue7ce": "\u60c5", "\ued49": "\u6837", "\uea39": "\u8d77", "\uee6a": "\u4ee3", "\ue143": "\u524d", "\ue747": "\u5173", "\ueb2b": "\u56db", "\ueaf2": "\u7528", "\ue383": "\u56e0", "\ued02": "\u771f", "\ueeb4": "\u5f00", "\ue9e2": "\u4eec", "\uefe6": "\u628a", "\ue3fb": "\u70b9", "\ue6f3": "\u540e", "\ue727": "\u4e66", "\ue9fa": "\u6b63", "\uea38": "\u8981", "\ue9a2": "\u90e8", "\ue545": "\u88ab", "\ued37": "\u8bdd", "\uef67": "\u6709", "\ue35f": "\u4e0a", "\ue732": "\u5b83", "\uecbc": "\u7ecf", "\ue37a": "\u8bf4", "\ueea3": "\u5916", "\ue231": "\u5b66", "\ueca2": "\u5bb6", "\ue776": "\u4e9b", "\uee81": "\u91cc", "\ue6eb": "\u76f8", "\ue299": "\u8eab", "\ue760": "\u4e8e", "\ueb05": "\u7406", "\uecf8": "\u5341", "\uea41": "\u770b", "\ue382": "\u4ec0", "\ue652": "\u4ed6", "\ue0af": "\u800c", "\ue92b": "\u5148", "\ueb7a": "\u65e0", "\ue3d7": "\u4e4b", "\ueb4b": "\u4e0e", "\uea71": "\u4e16", "\ue3e3": "\u5929", "\ue49e": "\u522b", "\ue781": "\u7136", "\ue132": "\u897f", "\ue9ac": "\u51e0", "\uefab": "\u591a", "\ue091": "\u4e8b", "\uec44": "\u65b0", "\ue888": "\u5728", "\uedb3": "\u6027", "\ue272": "\u4ee5", "\ue4b3": "\u5df1", "\ue648": "\u5411", "\ue8ad": "\u7684", "\ueb77": "\u9ad8", "\ued9b": "\u8005", "\ue58f": "\u89c1", "\ueae1": "\u5bf9", "\ue22e": "\u5c31", "\uebda": "\u6b7b", "\uea86": "\u95f4", "\uec05": "\u4ece", "\ue4b8": "\u8bba", "\ueac8": "\u7b49", "\ue079": "\u516c", "\ue7dc": "\u679c", "\ue7dd": "\u548c", "\ue6b7": "\u4f5c", "\ue8eb": "\u4eba", "\ue912": "\u6700", "\ue74c": "\u56fd", "\ue07c": "\u4e49", "\ueb9e": "\u601d", "\ue40e": "\u793e", "\ue104": "\u65b9", "\ue298": "\u957f", "\ue751": "\u624d", "\ue0c4": "\u56de", "\ue370": "\u5973", "\ue1a8": "\u4e48", "\uee24": "\u90a3", "\ue2c0": "\u5168", "\ue7e1": "\u540c", "\ue0d9": "\u6cd5", "\ue61a": "\u8fdb", "\ue3d3": "\u7269", "\ue716": "\u5f97", "\ue3e7": "\u767d", "\uef6c": "\u95e8", "\ue4f8": "\u518d", "\ue1b8": "\u79cd", "\ue976": "\u6587", "\ue86a": "\u5b9a", "\ue98d": "\u53c8", "\uec62": "\u9762", "\ue0e8": "\u53d1", "\ue203": "\u662f", "\ue84e": "\u4f60", "\ueea7": "\u6210", "\ue58c": "\u751f", "\ue963": "\u5230", "\ue81b": "\u5e76", "\ue75b": "\u5df2", "\ueead": "\u660e", "\uef4e": "\u53ea", "\ue595": "\u5fc3", "\ueee2": "\u4f1a", "\ue974": "\u5206", "\ue2f2": "\u7f8e", "\ue75f": "\u5f88", "\ue31b": "\u610f", "\ue323": "\u91cd", "\ue18d": "\u5f53", "\uea70": "\u4f46", "\ueae6": "\u5934", "\ue66d": "\u77e5", "\ue199": "\u4e3b", "\ue72f": "\u4f53", "\ue211": "\u542c", "\uedfd": "\u6253", "\ue24e": "\u672c"}