[{"\ue3b3": "\u60f3", "\ue4f5": "\u751f", "\uefe5": "\u5230", "\ue43e": "\u679c", "\ue9da": "\u660e", "\ue455": "\u8005", "\ue7cf": "\u73b0", "\ue9ed": "\u81ea", "\ue9e4": "\u8d70", "\ue834": "\u7269", "\ue8d5": "\u4f1a", "\ue6d5": "\u7531", "\ue807": "\u8fd8", "\ue95c": "\u5f97", "\ue0cb": "\u90fd", "\uedba": "\u6b63", "\ue693": "\u5411", "\ue2f7": "\u5b83", "\uee99": "\u7ed9", "\ue4d1": "\u77e5", "\uefd4": "\u6c11", "\ue7ba": "\u4eec", "\ue8fc": "\u6587", "\uef28": "\u4ec0", "\ue9a2": "\u6cd5", "\ue56b": "\u4ece", "\ue6cd": "\u53ef", "\ue344": "\u7528", "\ue484": "\u5168", "\ue3cf": "\u795e", "\ue7e8": "\u90a3", "\ue263": "\u5730", "\ue29b": "\u8fc7", "\ue697": "\u65b0", "\ue485": "\u4e0a", "\uede3": "\u591a", "\ue3f9": "\u5728", "\ue06e": "\u4e3b", "\ue4c1": "\u529b", "\ue7ad": "\u4f7f", "\ue3a3": "\u610f", "\ue354": "\u5bf9", "\ue5d7": "\u4e24", "\ueb54": "\u672c", "\uec00": "\u9ad8", "\uef7f": "\u4e49", "\uefcc": "\u8bba", "\ueb6b": "\u542c", "\ue42e": "\u773c", "\uea25": "\u624d", "\uee7f": "\u56fd", "\ue11d": "\u513f", "\ue383": "\u95ee", "\uef7e": "\u4fbf", "\ue896": "\u5b66", "\ue910": "\u58f0", "\uef52": "\u76f8", "\ue62e": "\u4e0e", "\ue37c": "\u5316", "\ue4b0": "\u53e3", "\ue193": "\u6709", "\uea9f": "\u7b11", "\ue27e": "\u770b", "\ueb8f": "\u89c1", "\uecf3": "\u4e66", "\ued63": "\u5df1", "\ue8af": "\u4e9b", "\ueae6": "\u4ed6", "\ue4bf": "\u66f4", "\ue0ec": "\u8981", "\ue39e": "\u4e0d", "\ue21a": "\u7b2c", "\ue17b": "\u52a8", "\ue169": "\u8fdb", "\uef73": "\u6700", "\ue67f": "\u5f53", "\ueea6": "\u8eab", "\ue372": "\u6240", "\ued79": "\u53c8", "\uec11": "\u5c0f", "\uecf0": "\u88ab", "\ue4a1": "\u53f2", "\ue731": "\u4ee5", "\ueb18": "\u540c", "\ue808": "\u5b50", "\ue58f": "\u592a", "\uec09": "\u65f6", "\ue640": "\u4e2a", "\ue581": "\u6027", "\ue989": "\u4f60", "\ue827": "\u518d", "\uef05": "\u5c06", "\ueb83": "\u6211", "\ue6e9": "\u5e76", "\ue587": "\u5bb6", "\ue435": "\u5f00", "\ue6ee": "\u5934", "\ue966": "\u8001", "\ue525": "\u8d77", "\ue648": "\u8bf4", "\ue839": "\u793e", "\ue668": "\u4e0b", "\ue4d4": "\u5927", "\ue557": "\u5929", "\ue174": "\u4f55", "\ue41c": "\u5199", "\uef9f": "\u4f53", "\ue0af": "\u5df2", "\ue18a": "\u4e8e", "\ue752": "\u5979", "\ue486": "\u548c", "\ue0be": "\u4e4b", "\ue175": "\u6c14", "\ue61f": "\u6b7b", "\ue78b": "\u51fa", "\ue780": "\u4e8b", "\ue916": "\u7406", "\ue052": "\u7f8e", "\ue6e1": "\u91cd", "\ue820": "\u4e09", "\ue7f5": "\u800c", "\ue563": "\u5173", "\ue5a3": "\u4e2d", "\ue2e2": "\u624b", "\ue5fd": "\u6210", "\ue6fc": "\u5b9a", "\uee9b": "\u4e48", "\ue894": "\u6b64", "\ue1c4": "\u51e0", "\ue7b9": "\u4e5f", "\ue831": "\u5341", "\ue156": "\u597d", "\ueb39": "\u56de", "\uee15": "\u80fd", "\ue016": "\u5c11", "\ue4ba": "\u4eba", "\ue907": "\u4f5c", "\ue8c1": "\u5148", "\ued1f": "\u9762", "\ue548": "\u53ea", "\ue77a": "\u8fd9", "\ueae9": "\u7ecf", "\ue76b": "\u5e74", "\ue089": "\u95e8", "\ue85e": "\u6837", "\ue8a2": "\u70b9", "\ued12": "\u611f", "\ue771": "\u79cd", "\ueeb7": "\u4e16", "\ue857": "\u56db", "\ue726": "\u7740", "\ue6dc": "\u4e00", "\uea14": "\u5973", "\ue423": "\u8bdd", "\uec84": "\u516c", "\ue8ba": "\u56e0", "\ueaca": "\u601d", "\ue8e9": "\u884c", "\ueae2": "\u771f", "\ue365": "\u540d", "\ue50e": "\u5f88", "\ue8d2": "\u95f4", "\uee6a": "\u6765", "\ue9e5": "\u5982", "\ueec5": "\u4e3a", "\ue48f": "\u7136", "\ue9d1": "\u628a", "\ue797": "\u897f", "\uedf6": "\u4ee3", "\ued7e": "\u4e8c", "\ue427": "\u767d", "\ue249": "\u662f", "\ueffc": "\u53d1", "\ue2f8": "\u5206", "\ued33": "\u90e8", "\ue8b7": "\u7b49", "\ued08": "\u53bb", "\ue7ff": "\u524d", "\uef33": "\u4f46", "\ue5ce": "\u522b", "\ue7c8": "\u6253", "\uea85": "\u6ca1", "\uee83": "\u4e86", "\uea8e": "\u7684", "\ueaaa": "\u5c31", "\uef16": "\u6559", "\uea9b": "\u5fc3", "\ue0ef": "\u5b9e", "\ue223": "\u65e5", "\ueaa3": "\u65b9", "\ue1d6": "\u65e0", "\uea9e": "\u5916", "\ue389": "\u5374", "\ueb23": "\u9053", "\uea8d": "\u540e", "\ue82e": "\u957f", "\ue25b": "\u91cc", "\ue36a": "\u7279", "\ueafe": "\u60c5", "\uee4a": "\u5176"}, 193.4527317847651]